Workbook

Sheet License & Disclaimer
A1: License & Disclaimer
A2: License | B2: Apache License 2.0 - https://www.apache.org/licenses/LICENSE-2.0
A3: Copyright | B3: Copyright 2026 Mayank
A4: Version | B4: 0.1.0 (2026-10-21)
A5: Disclaimer | B5: Not legal or audit advice. Requirement text is a condensed paraphrase; verify against the authoritative source. CIA classifications, domain groupings and cross-framework mappings are expert judgement. Provided AS IS. Standards referenced remain the property of their publishers; see NOTICE and DISCLAIMER.md.
A6: OWASP LLM Top 10 | B6: (c) OWASP Foundation, CC BY-SA 4.0; paraphrased, attribution required.
A7: MITRE ATLAS | B7: (c) The MITRE Corporation; Apache-2.0.
A8: ISO/IEC | B8: (c) ISO/IEC; referenced by clause number and paraphrased only.
A9: Examples | B9: Rows with Row ID 'EX-*' in tab 19 are fictional examples.

Sheet Summary
A1: Compliance Summary
A3: Group | B3: Total items | C3: Not started | D3: In progress | E3: Implemented | F3: Verified | G3: Not applicable | H3: % Complete (Impl.+Verified / applicable)
A4: CIA-security: Clauses 4-10 | B4: =SUM(C4:G4) -> 5 | C4: =COUNTIFS('1 CIA-Security Controls'!$L$4:$L$23,"Not started",'1 CIA-Security Controls'!$B$4:$B$23,"Clause") -> 5 | D4: =COUNTIFS('1 CIA-Security Controls'!$L$4:$L$23,"In progress",'1 CIA-Security Controls'!$B$4:$B$23,"Clause") -> 0 | E4: =COUNTIFS('1 CIA-Security Controls'!$L$4:$L$23,"Implemented",'1 CIA-Security Controls'!$B$4:$B$23,"Clause") -> 0 | F4: =COUNTIFS('1 CIA-Security Controls'!$L$4:$L$23,"Verified",'1 CIA-Security Controls'!$B$4:$B$23,"Clause") -> 0 | G4: =COUNTIFS('1 CIA-Security Controls'!$L$4:$L$23,"Not applicable",'1 CIA-Security Controls'!$B$4:$B$23,"Clause") -> 0 | H4: =IFERROR((E4+F4)/(B4-G4),0) -> 0
A5: CIA-security: Annex A | B5: =SUM(C5:G5) -> 13 | C5: =COUNTIFS('1 CIA-Security Controls'!$L$4:$L$23,"Not started",'1 CIA-Security Controls'!$B$4:$B$23,"Annex A") -> 13 | D5: =COUNTIFS('1 CIA-Security Controls'!$L$4:$L$23,"In progress",'1 CIA-Security Controls'!$B$4:$B$23,"Annex A") -> 0 | E5: =COUNTIFS('1 CIA-Security Controls'!$L$4:$L$23,"Implemented",'1 CIA-Security Controls'!$B$4:$B$23,"Annex A") -> 0 | F5: =COUNTIFS('1 CIA-Security Controls'!$L$4:$L$23,"Verified",'1 CIA-Security Controls'!$B$4:$B$23,"Annex A") -> 0 | G5: =COUNTIFS('1 CIA-Security Controls'!$L$4:$L$23,"Not applicable",'1 CIA-Security Controls'!$B$4:$B$23,"Annex A") -> 0 | H5: =IFERROR((E5+F5)/(B5-G5),0) -> 0
A6: CIA-security TOTAL | B6: =B4+B5 -> 18 | C6: =C4+C5 -> 18 | D6: =D4+D5 -> 0 | E6: =E4+E5 -> 0 | F6: =F4+F5 -> 0 | G6: =G4+G5 -> 0 | H6: =IFERROR((E6+F6)/(B6-G6),0) -> 0
A7: Non-CIA: Clauses 4-10 | B7: =SUM(C7:G7) -> 27 | C7: =COUNTIFS('2 Non-CIA (Other) Controls'!$I$4:$I$57,"Not started",'2 Non-CIA (Other) Controls'!$B$4:$B$57,"Clause") -> 27 | D7: =COUNTIFS('2 Non-CIA (Other) Controls'!$I$4:$I$57,"In progress",'2 Non-CIA (Other) Controls'!$B$4:$B$57,"Clause") -> 0 | E7: =COUNTIFS('2 Non-CIA (Other) Controls'!$I$4:$I$57,"Implemented",'2 Non-CIA (Other) Controls'!$B$4:$B$57,"Clause") -> 0 | F7: =COUNTIFS('2 Non-CIA (Other) Controls'!$I$4:$I$57,"Verified",'2 Non-CIA (Other) Controls'!$B$4:$B$57,"Clause") -> 0 | G7: =COUNTIFS('2 Non-CIA (Other) Controls'!$I$4:$I$57,"Not applicable",'2 Non-CIA (Other) Controls'!$B$4:$B$57,"Clause") -> 0 | H7: =IFERROR((E7+F7)/(B7-G7),0) -> 0
A8: Non-CIA: Annex A | B8: =SUM(C8:G8) -> 25 | C8: =COUNTIFS('2 Non-CIA (Other) Controls'!$I$4:$I$57,"Not started",'2 Non-CIA (Other) Controls'!$B$4:$B$57,"Annex A") -> 25 | D8: =COUNTIFS('2 Non-CIA (Other) Controls'!$I$4:$I$57,"In progress",'2 Non-CIA (Other) Controls'!$B$4:$B$57,"Annex A") -> 0 | E8: =COUNTIFS('2 Non-CIA (Other) Controls'!$I$4:$I$57,"Implemented",'2 Non-CIA (Other) Controls'!$B$4:$B$57,"Annex A") -> 0 | F8: =COUNTIFS('2 Non-CIA (Other) Controls'!$I$4:$I$57,"Verified",'2 Non-CIA (Other) Controls'!$B$4:$B$57,"Annex A") -> 0 | G8: =COUNTIFS('2 Non-CIA (Other) Controls'!$I$4:$I$57,"Not applicable",'2 Non-CIA (Other) Controls'!$B$4:$B$57,"Annex A") -> 0 | H8: =IFERROR((E8+F8)/(B8-G8),0) -> 0
A9: Non-CIA TOTAL | B9: =B7+B8 -> 52 | C9: =C7+C8 -> 52 | D9: =D7+D8 -> 0 | E9: =E7+E8 -> 0 | F9: =F7+F8 -> 0 | G9: =G7+G8 -> 0 | H9: =IFERROR((E9+F9)/(B9-G9),0) -> 0
A10: OVERALL | B10: =B6+B9 -> 70 | C10: =C6+C9 -> 70 | D10: =D6+D9 -> 0 | E10: =E6+E9 -> 0 | F10: =F6+F9 -> 0 | G10: =G6+G9 -> 0 | H10: =IFERROR((E10+F10)/(B10-G10),0) -> 0
A12: CIA coverage of the CIA-security items | B12: Count
A13: Confidentiality (C) | B13: =COUNTIF('1 CIA-Security Controls'!$E$4:$E$23,"●") -> 15
A14: Integrity (I) | B14: =COUNTIF('1 CIA-Security Controls'!$F$4:$F$23,"●") -> 18
A15: Availability (A) | B15: =COUNTIF('1 CIA-Security Controls'!$G$4:$G$23,"●") -> 15
A16: All three (C+I+A) | B16: =COUNTIFS('1 CIA-Security Controls'!$E$4:$E$23,"●",'1 CIA-Security Controls'!$F$4:$F$23,"●",'1 CIA-Security Controls'!$G$4:$G$23,"●") -> 14
A18: EU AI Act
A19: Group | B19: Total items | C19: Not started | D19: In progress | E19: Implemented | F19: Verified | G19: Not applicable | H19: % Complete (Impl.+Verified / applicable)
A20: EU AI Act - all items | B20: =SUM(C20:G20) -> 34 | C20: =COUNTIF('3 EU AI Act'!$K$14:$K$56,"Not started") -> 34 | D20: =COUNTIF('3 EU AI Act'!$K$14:$K$56,"In progress") -> 0 | E20: =COUNTIF('3 EU AI Act'!$K$14:$K$56,"Implemented") -> 0 | F20: =COUNTIF('3 EU AI Act'!$K$14:$K$56,"Verified") -> 0 | G20: =COUNTIF('3 EU AI Act'!$K$14:$K$56,"Not applicable") -> 0 | H20: =IFERROR((E20+F20)/(B20-G20),0) -> 0
A21: EU AI Act - CIA-security items | B21: =SUMPRODUCT(--(( '3 EU AI Act'!E14:E56<>"")+('3 EU AI Act'!F14:F56<>"")+('3 EU AI Act'!G14:G56<>"")>0)) -> 12
A23: OECD AI Principles
A24: Group | B24: Total items | C24: Not started | D24: In progress | E24: Implemented | F24: Verified | G24: Not applicable | H24: % Complete (Impl.+Verified / applicable)
A25: OECD - all items | B25: =SUM(C25:G25) -> 14 | C25: =COUNTIF('4 OECD AI Principles'!$J$4:$J$20,"Not started") -> 14 | D25: =COUNTIF('4 OECD AI Principles'!$J$4:$J$20,"In progress") -> 0 | E25: =COUNTIF('4 OECD AI Principles'!$J$4:$J$20,"Implemented") -> 0 | F25: =COUNTIF('4 OECD AI Principles'!$J$4:$J$20,"Verified") -> 0 | G25: =COUNTIF('4 OECD AI Principles'!$J$4:$J$20,"Not applicable") -> 0 | H25: =IFERROR((E25+F25)/(B25-G25),0) -> 0
A26: OECD - CIA-security items | B26: =SUMPRODUCT(--(('4 OECD AI Principles'!D4:D20<>"")+('4 OECD AI Principles'!E4:E20<>"")+('4 OECD AI Principles'!F4:F20<>"")>0)) -> 3
A28: NIST AI RMF
A29: Group | B29: Total items | C29: Not started | D29: In progress | E29: Implemented | F29: Verified | G29: Not applicable | H29: % Complete (Impl.+Verified / applicable)
A30: NIST AI RMF - all items | B30: =SUM(C30:G30) -> 19 | C30: =COUNTIF('5 NIST AI RMF'!$J$4:$J$26,"Not started") -> 19 | D30: =COUNTIF('5 NIST AI RMF'!$J$4:$J$26,"In progress") -> 0 | E30: =COUNTIF('5 NIST AI RMF'!$J$4:$J$26,"Implemented") -> 0 | F30: =COUNTIF('5 NIST AI RMF'!$J$4:$J$26,"Verified") -> 0 | G30: =COUNTIF('5 NIST AI RMF'!$J$4:$J$26,"Not applicable") -> 0 | H30: =IFERROR((E30+F30)/(B30-G30),0) -> 0
A31: NIST AI RMF - CIA-security items | B31: =SUMPRODUCT(--(('5 NIST AI RMF'!D4:D26<>"")+('5 NIST AI RMF'!E4:E26<>"")+('5 NIST AI RMF'!F4:F26<>"")>0)) -> 6
A33: ISO/IEC 42005
A34: Group | B34: Total items | C34: Not started | D34: In progress | E34: Implemented | F34: Verified | G34: Not applicable | H34: % Complete (Impl.+Verified / applicable)
A35: ISO 42005 - all items | B35: =SUM(C35:G35) -> 21 | C35: =COUNTIF('6 ISO 42005 Impact Assessment'!$J$4:$J$28,"Not started") -> 21 | D35: =COUNTIF('6 ISO 42005 Impact Assessment'!$J$4:$J$28,"In progress") -> 0 | E35: =COUNTIF('6 ISO 42005 Impact Assessment'!$J$4:$J$28,"Implemented") -> 0 | F35: =COUNTIF('6 ISO 42005 Impact Assessment'!$J$4:$J$28,"Verified") -> 0 | G35: =COUNTIF('6 ISO 42005 Impact Assessment'!$J$4:$J$28,"Not applicable") -> 0 | H35: =IFERROR((E35+F35)/(B35-G35),0) -> 0
A36: ISO 42005 - CIA-security items | B36: =SUMPRODUCT(--(('6 ISO 42005 Impact Assessment'!D4:D28<>"")+('6 ISO 42005 Impact Assessment'!E4:E28<>"")+('6 ISO 42005 Impact Assessment'!F4:F28<>"")>0)) -> 3
A38: ISO/IEC 27001:2022
A39: Group | B39: Total items | C39: Not started | D39: In progress | E39: Implemented | F39: Verified | G39: Not applicable | H39: % Complete (Impl.+Verified / applicable)
A40: ISO 27001 - all items | B40: =SUM(C40:G40) -> 123 | C40: =COUNTIF('7 ISO 27001'!$J$4:$J$139,"Not started") -> 123 | D40: =COUNTIF('7 ISO 27001'!$J$4:$J$139,"In progress") -> 0 | E40: =COUNTIF('7 ISO 27001'!$J$4:$J$139,"Implemented") -> 0 | F40: =COUNTIF('7 ISO 27001'!$J$4:$J$139,"Verified") -> 0 | G40: =COUNTIF('7 ISO 27001'!$J$4:$J$139,"Not applicable") -> 0 | H40: =IFERROR((E40+F40)/(B40-G40),0) -> 0
A41: ISO 27001 - CIA-security items | B41: =SUMPRODUCT(--(('7 ISO 27001'!D4:D139<>"")+('7 ISO 27001'!E4:E139<>"")+('7 ISO 27001'!F4:F139<>"")>0)) -> 85
A43: ISO/IEC 17021-1
A44: Group | B44: Total items | C44: Not started | D44: In progress | E44: Implemented | F44: Verified | G44: Not applicable | H44: % Complete (Impl.+Verified / applicable)
A45: ISO 17021 - all items | B45: =SUM(C45:G45) -> 42 | C45: =COUNTIF('8 ISO 17021 Alignment'!$L$4:$L$52,"Not started") -> 42 | D45: =COUNTIF('8 ISO 17021 Alignment'!$L$4:$L$52,"In progress") -> 0 | E45: =COUNTIF('8 ISO 17021 Alignment'!$L$4:$L$52,"Implemented") -> 0 | F45: =COUNTIF('8 ISO 17021 Alignment'!$L$4:$L$52,"Verified") -> 0 | G45: =COUNTIF('8 ISO 17021 Alignment'!$L$4:$L$52,"Not applicable") -> 0 | H45: =IFERROR((E45+F45)/(B45-G45),0) -> 0
A46: ISO 17021 - CIA-security items | B46: =SUMPRODUCT(--(('8 ISO 17021 Alignment'!F4:F52<>"")+('8 ISO 17021 Alignment'!G4:G52<>"")+('8 ISO 17021 Alignment'!H4:H52<>"")>0)) -> 11
A48: GDPR
A49: Group | B49: Total items | C49: Not started | D49: In progress | E49: Implemented | F49: Verified | G49: Not applicable | H49: % Complete (Impl.+Verified / applicable)
A50: GDPR - all items | B50: =SUM(C50:G50) -> 39 | C50: =COUNTIF('9 GDPR'!$J$4:$J$51,"Not started") -> 39 | D50: =COUNTIF('9 GDPR'!$J$4:$J$51,"In progress") -> 0 | E50: =COUNTIF('9 GDPR'!$J$4:$J$51,"Implemented") -> 0 | F50: =COUNTIF('9 GDPR'!$J$4:$J$51,"Verified") -> 0 | G50: =COUNTIF('9 GDPR'!$J$4:$J$51,"Not applicable") -> 0 | H50: =IFERROR((E50+F50)/(B50-G50),0) -> 0
A51: GDPR - CIA-security items | B51: =SUMPRODUCT(--(('9 GDPR'!D4:D51<>"")+('9 GDPR'!E4:E51<>"")+('9 GDPR'!F4:F51<>"")>0)) -> 13
A53: OWASP Top 10 for LLM Applications
A54: Group | B54: Total items | C54: Not started | D54: In progress | E54: Implemented | F54: Verified | G54: Not applicable | H54: % Complete (Impl.+Verified / applicable)
A55: OWASP LLM Top 10 - all risks | B55: =SUM(C55:G55) -> 10 | C55: =COUNTIF('10 OWASP LLM Top 10'!$K$4:$K$13,"Not started") -> 10 | D55: =COUNTIF('10 OWASP LLM Top 10'!$K$4:$K$13,"In progress") -> 0 | E55: =COUNTIF('10 OWASP LLM Top 10'!$K$4:$K$13,"Implemented") -> 0 | F55: =COUNTIF('10 OWASP LLM Top 10'!$K$4:$K$13,"Verified") -> 0 | G55: =COUNTIF('10 OWASP LLM Top 10'!$K$4:$K$13,"Not applicable") -> 0 | H55: =IFERROR((E55+F55)/(B55-G55),0) -> 0
A57: ISO/IEC 27701
A58: Group | B58: Total items | C58: Not started | D58: In progress | E58: Implemented | F58: Verified | G58: Not applicable | H58: % Complete (Impl.+Verified / applicable)
A59: ISO 27701 - all items | B59: =SUM(C59:G59) -> 22 | C59: =COUNTIF('11 ISO 27701 PIMS'!$J$4:$J$29,"Not started") -> 22 | D59: =COUNTIF('11 ISO 27701 PIMS'!$J$4:$J$29,"In progress") -> 0 | E59: =COUNTIF('11 ISO 27701 PIMS'!$J$4:$J$29,"Implemented") -> 0 | F59: =COUNTIF('11 ISO 27701 PIMS'!$J$4:$J$29,"Verified") -> 0 | G59: =COUNTIF('11 ISO 27701 PIMS'!$J$4:$J$29,"Not applicable") -> 0 | H59: =IFERROR((E59+F59)/(B59-G59),0) -> 0
A60: ISO 27701 - CIA-security items | B60: =SUMPRODUCT(--(('11 ISO 27701 PIMS'!D4:D29<>"")+('11 ISO 27701 PIMS'!E4:E29<>"")+('11 ISO 27701 PIMS'!F4:F29<>"")>0)) -> 7
A62: Master Control List (all frameworks combined)
A63: Group | B63: Total items | C63: Not started | D63: In progress | E63: Implemented | F63: Verified | G63: Not applicable | H63: % Complete (Impl.+Verified / applicable)
A64: All frameworks - total unique control items | B64: =SUM(C64:G64) -> 557 | C64: =COUNTIF('12 Master Control List'!$J$4:$J$592,"Not started") -> 557 | D64: =COUNTIF('12 Master Control List'!$J$4:$J$592,"In progress") -> 0 | E64: =COUNTIF('12 Master Control List'!$J$4:$J$592,"Implemented") -> 0 | F64: =COUNTIF('12 Master Control List'!$J$4:$J$592,"Verified") -> 0 | G64: =COUNTIF('12 Master Control List'!$J$4:$J$592,"Not applicable") -> 0 | H64: =IFERROR((E64+F64)/(B64-G64),0) -> 0
A65: Common control domains identified | B65: 32
A67: Privacy by Design
A68: Group | B68: Total items | C68: Not started | D68: In progress | E68: Implemented | F68: Verified | G68: Not applicable | H68: % Complete (Impl.+Verified / applicable)
A69: Privacy by Design - all items | B69: =SUM(C69:G69) -> 20 | C69: =COUNTIF('14 Privacy by Design'!$J$4:$J$30,"Not started") -> 20 | D69: =COUNTIF('14 Privacy by Design'!$J$4:$J$30,"In progress") -> 0 | E69: =COUNTIF('14 Privacy by Design'!$J$4:$J$30,"Implemented") -> 0 | F69: =COUNTIF('14 Privacy by Design'!$J$4:$J$30,"Verified") -> 0 | G69: =COUNTIF('14 Privacy by Design'!$J$4:$J$30,"Not applicable") -> 0 | H69: =IFERROR((E69+F69)/(B69-G69),0) -> 0
A70: Privacy by Design - CIA-security items | B70: =SUMPRODUCT(--(('14 Privacy by Design'!D4:D30<>"")+('14 Privacy by Design'!E4:E30<>"")+('14 Privacy by Design'!F4:F30<>"")>0)) -> 9
A72: ISO/IEC 31700-1/-2
A73: Group | B73: Total items | C73: Not started | D73: In progress | E73: Implemented | F73: Verified | G73: Not applicable | H73: % Complete (Impl.+Verified / applicable)
A74: ISO 31700 - all items | B74: =SUM(C74:G74) -> 28 | C74: =COUNTIF('15 ISO 31700 PbD (Consumer)'!$J$4:$J$37,"Not started") -> 28 | D74: =COUNTIF('15 ISO 31700 PbD (Consumer)'!$J$4:$J$37,"In progress") -> 0 | E74: =COUNTIF('15 ISO 31700 PbD (Consumer)'!$J$4:$J$37,"Implemented") -> 0 | F74: =COUNTIF('15 ISO 31700 PbD (Consumer)'!$J$4:$J$37,"Verified") -> 0 | G74: =COUNTIF('15 ISO 31700 PbD (Consumer)'!$J$4:$J$37,"Not applicable") -> 0 | H74: =IFERROR((E74+F74)/(B74-G74),0) -> 0
A75: ISO 31700 - CIA-security items | B75: =SUMPRODUCT(--(('15 ISO 31700 PbD (Consumer)'!D4:D37<>"")+('15 ISO 31700 PbD (Consumer)'!E4:E37<>"")+('15 ISO 31700 PbD (Consumer)'!F4:F37<>"")>0)) -> 14
A77: DORA
A78: Group | B78: Total items | C78: Not started | D78: In progress | E78: Implemented | F78: Verified | G78: Not applicable | H78: % Complete (Impl.+Verified / applicable)
A79: DORA - all items | B79: =SUM(C79:G79) -> 29 | C79: =COUNTIF('16 DORA'!$J$4:$J$40,"Not started") -> 29 | D79: =COUNTIF('16 DORA'!$J$4:$J$40,"In progress") -> 0 | E79: =COUNTIF('16 DORA'!$J$4:$J$40,"Implemented") -> 0 | F79: =COUNTIF('16 DORA'!$J$4:$J$40,"Verified") -> 0 | G79: =COUNTIF('16 DORA'!$J$4:$J$40,"Not applicable") -> 0 | H79: =IFERROR((E79+F79)/(B79-G79),0) -> 0
A80: DORA - CIA-security items | B80: =SUMPRODUCT(--(('16 DORA'!D4:D40<>"")+('16 DORA'!E4:E40<>"")+('16 DORA'!F4:F40<>"")>0)) -> 18
A82: NIST ARIA
A83: Group | B83: Total items | C83: Not started | D83: In progress | E83: Implemented | F83: Verified | G83: Not applicable | H83: % Complete (Impl.+Verified / applicable)
A84: NIST ARIA - all items | B84: =SUM(C84:G84) -> 14 | C84: =COUNTIF('17 NIST ARIA'!$J$4:$J$23,"Not started") -> 14 | D84: =COUNTIF('17 NIST ARIA'!$J$4:$J$23,"In progress") -> 0 | E84: =COUNTIF('17 NIST ARIA'!$J$4:$J$23,"Implemented") -> 0 | F84: =COUNTIF('17 NIST ARIA'!$J$4:$J$23,"Verified") -> 0 | G84: =COUNTIF('17 NIST ARIA'!$J$4:$J$23,"Not applicable") -> 0 | H84: =IFERROR((E84+F84)/(B84-G84),0) -> 0
A85: NIST ARIA - CIA-security items | B85: =SUMPRODUCT(--(('17 NIST ARIA'!D4:D23<>"")+('17 NIST ARIA'!E4:E23<>"")+('17 NIST ARIA'!F4:F23<>"")>0)) -> 6
A87: FAIR Risk Methodology
A88: Group | B88: Total items | C88: Not started | D88: In progress | E88: Implemented | F88: Verified | G88: Not applicable | H88: % Complete (Impl.+Verified / applicable)
A89: FAIR - all items | B89: =SUM(C89:G89) -> 24 | C89: =COUNTIF('18 FAIR Risk Methodology'!$J$4:$J$30,"Not started") -> 24 | D89: =COUNTIF('18 FAIR Risk Methodology'!$J$4:$J$30,"In progress") -> 0 | E89: =COUNTIF('18 FAIR Risk Methodology'!$J$4:$J$30,"Implemented") -> 0 | F89: =COUNTIF('18 FAIR Risk Methodology'!$J$4:$J$30,"Verified") -> 0 | G89: =COUNTIF('18 FAIR Risk Methodology'!$J$4:$J$30,"Not applicable") -> 0 | H89: =IFERROR((E89+F89)/(B89-G89),0) -> 0
A90: FAIR - CIA-security items | B90: =SUMPRODUCT(--(('18 FAIR Risk Methodology'!D4:D30<>"")+('18 FAIR Risk Methodology'!E4:E30<>"")+('18 FAIR Risk Methodology'!F4:F30<>"")>0)) -> 13
A92: ISO/IEC 5181
A93: Group | B93: Total items | C93: Not started | D93: In progress | E93: Implemented | F93: Verified | G93: Not applicable | H93: % Complete (Impl.+Verified / applicable)
A94: ISO 5181 - all items | B94: =SUM(C94:G94) -> 13 | C94: =COUNTIF('20 ISO 5181 Data Provenance'!$J$4:$J$19,"Not started") -> 13 | D94: =COUNTIF('20 ISO 5181 Data Provenance'!$J$4:$J$19,"In progress") -> 0 | E94: =COUNTIF('20 ISO 5181 Data Provenance'!$J$4:$J$19,"Implemented") -> 0 | F94: =COUNTIF('20 ISO 5181 Data Provenance'!$J$4:$J$19,"Verified") -> 0 | G94: =COUNTIF('20 ISO 5181 Data Provenance'!$J$4:$J$19,"Not applicable") -> 0 | H94: =IFERROR((E94+F94)/(B94-G94),0) -> 0
A95: ISO 5181 - CIA-security items | B95: =SUMPRODUCT(--(('20 ISO 5181 Data Provenance'!D4:D19<>"")+('20 ISO 5181 Data Provenance'!E4:E19<>"")+('20 ISO 5181 Data Provenance'!F4:F19<>"")>0)) -> 8
A97: ISO/IEC 27090
A98: Group | B98: Total items | C98: Not started | D98: In progress | E98: Implemented | F98: Verified | G98: Not applicable | H98: % Complete (Impl.+Verified / applicable)
A99: ISO 27090 - all items | B99: =SUM(C99:G99) -> 17 | C99: =COUNTIF('21 ISO 27090 AI Threats'!$J$4:$J$24,"Not started") -> 17 | D99: =COUNTIF('21 ISO 27090 AI Threats'!$J$4:$J$24,"In progress") -> 0 | E99: =COUNTIF('21 ISO 27090 AI Threats'!$J$4:$J$24,"Implemented") -> 0 | F99: =COUNTIF('21 ISO 27090 AI Threats'!$J$4:$J$24,"Verified") -> 0 | G99: =COUNTIF('21 ISO 27090 AI Threats'!$J$4:$J$24,"Not applicable") -> 0 | H99: =IFERROR((E99+F99)/(B99-G99),0) -> 0
A100: ISO 27090 - CIA-security items | B100: =SUMPRODUCT(--(('21 ISO 27090 AI Threats'!D4:D24<>"")+('21 ISO 27090 AI Threats'!E4:E24<>"")+('21 ISO 27090 AI Threats'!F4:F24<>"")>0)) -> 12
A102: MITRE ATLAS
A103: Group | B103: Total items | C103: Not started | D103: In progress | E103: Implemented | F103: Verified | G103: Not applicable | H103: % Complete (Impl.+Verified / applicable)
A104: MITRE ATLAS - all tactics | B104: =SUM(C104:G104) -> 18 | C104: =COUNTIF('22 MITRE ATLAS'!$J$4:$J$23,"Not started") -> 18 | D104: =COUNTIF('22 MITRE ATLAS'!$J$4:$J$23,"In progress") -> 0 | E104: =COUNTIF('22 MITRE ATLAS'!$J$4:$J$23,"Implemented") -> 0 | F104: =COUNTIF('22 MITRE ATLAS'!$J$4:$J$23,"Verified") -> 0 | G104: =COUNTIF('22 MITRE ATLAS'!$J$4:$J$23,"Not applicable") -> 0 | H104: =IFERROR((E104+F104)/(B104-G104),0) -> 0
A105: MITRE ATLAS - CIA-marked tactics | B105: =SUMPRODUCT(--(('22 MITRE ATLAS'!D4:D23<>"")+('22 MITRE ATLAS'!E4:E23<>"")+('22 MITRE ATLAS'!F4:F23<>"")>0)) -> 15

Sheet Read Me
A1: ISO/IEC 42001:2023 (AIMS) - CIA-Security vs Remaining Controls Checklist
A3: Scope: Clauses 4-10 (32 items) and Annex A (38 controls), segregated into two working sheets so security effort is clearly separated from the rest.
A4: Sheet 1 - CIA-Security Controls: items whose primary purpose is to protect the Confidentiality, Integrity or Availability of information/AI assets (data, models, code, infrastructure, logs, documented information). Columns C / I / A show which property each item protects. These need security ownership (CISO/security architecture) and technical evidence.
A5: Sheet 2 - Non-CIA (Other) Controls: governance, leadership, risk planning (general), impact assessment on individuals/society, fairness/ethics, transparency, competence, documentation, performance evaluation, improvement. Owned by AI governance, compliance, legal, HR, product. Column F notes where an item still enables security indirectly.
A6: Judgement rule: an item is CIA-security only if a failure of the requirement would directly expose AI assets to unauthorized access/disclosure (C), unauthorized alteration/poisoning/loss of trustworthiness (I), or loss of access/service (A). Privacy/lawfulness of data use is treated as governance unless the requirement itself is about protecting the data.
A7: The classification is expert judgement for audit planning, not part of the standard. Adjust to your risk assessment; move a row between sheets if your context requires.
A8: How to use: set 'Applicable (SoA)', track 'Status', assign Owner, note gaps. Clauses 4-10 are mandatory; Annex A exclusions need justification (clause 6.1.3). Requirement text is a condensed paraphrase - verify against ISO/IEC 42001:2023 (Annex B guidance).
A9: Counts: CIA-security = 18 items; Non-CIA = 52 items; total = 70.
A10: Tab 3 - EU AI Act: 34 articles/annex items relevant to security governance and high-risk AI compliance, of which 12 are marked CIA-security (mainly Art.15 Accuracy/Robustness/Cybersecurity, Art.9 risk management, Art.10 data governance, Art.12/19 logging, Art.26 deployer logging/monitoring, Art.55 GPAI systemic-risk cybersecurity, Art.72 post-market monitoring, Art.73 incident reporting).
A11: Tab 4 - OECD AI Principles (updated May 2024): 14 items across the 5 values-based principles, 5 policy recommendations and 4 update focus areas, of which 3 are marked CIA-security (mainly 1.4 Robustness, security and safety, plus 1.2 privacy and 1.5 accountability/traceability).
A12: Tab 5 - NIST AI RMF 1.0 (NIST.AI.100-1): 19 categories across GOVERN (6), MAP (5), MEASURE (4) and MANAGE (4) - the framework's full structure is 19 categories / 72 subcategories; this tab tracks at category level. 6 categories are marked CIA-security (Govern 6, Map 4 and Manage 3 - third-party/supply-chain risk; Measure 2 - secure & resilient testing; Measure 3 - risk tracking/monitoring; Manage 4 - incident response and recovery). Suggested actions are condensed from the AI RMF Playbook; verify against NIST.AI.100-1 and the Playbook for subcategory-level detail.
A13: Tab 6 - ISO/IEC 42005:2025 (AI System Impact Assessment guidance): 21 items covering Clause 5 (developing/implementing the AISIA process), Clause 6 (documenting the AISIA) and the informative annexes (incl. Annex A linking to ISO/IEC 42001 clauses 6.1.2/6.1.4/A.5, Annex B linking to ISO/IEC 23894, and the Annex E AISIA template). 3 items are marked CIA-security (impact identification covering security-related harms, integrity of assessment records, confidentiality/access control of records). ISO/IEC 42005 is a guidance document (not a certifiable requirements standard); Clause 5/6 sub-points here are a thematic breakdown of its content, not verbatim numbered subclauses - verify structure and wording against the purchased standard.
... A31: Tab 22 - MITRE ATLAS (Adversarial Threat Landscape for Artificial-Intelligence Systems): 18 items covering all 16 current ATLAS tactics (Reconnaissance, Resource Development, Initial Access, AI Model Access, Execution, Persistence, Privilege Escalation, Defense Evasion, Credential Access, Discovery, Lateral Movement, Collection, AI Attack Staging, Command and Control, Exfiltration, Impact), verified current as of October 2026. ATLAS mirrors MITRE ATT&CK's structure (tactics as adversary objectives/columns, techniques as methods/rows beneath each, linked to real-world case studies) but is AI/ML-specific; 'AI Model Access' and 'AI Attack Staging' are the two tactics with no direct ATT&CK equivalent and carry the AI-native logic. This tab is deliberately at tactic level (16 rows) rather than enumerating the full ~100+ techniques/sub-techniques, to match the granularity used elsewhere in this workbook - for hands-on red-teaming or detection-engineering work, consult the live matrix at atlas.mitre.org for the current technique list under each tactic, since ATLAS is actively updated (recent releases have added agentic-AI and multi-agent techniques at a fast pace). 15 items are marked CIA-security (Resource Development is the one exception, being purely attacker-side preparation with no direct impact on the target yet). IMPORTANT: ATLAS is a threat-intelligence and red-team/detection reference, not a certifiable compliance checklist like the other standards in this workbook - use it to structure red-team scope and SOC detection use cases, and cross-walk it against your own AI architecture rather than treating every tactic as a control to 'complete'. It complements Tab 10 (OWASP LLM Top 10, which gives the vulnerability-centric view) and Tab 21 (ISO/IEC 27090, which gives the ISO-governance threat view) - ATLAS adds the adversary's full attack-lifecycle perspective with documented real-world case studies behind each technique.

Sheet 1 CIA-Security Controls
A1: ISO/IEC 42001:2023 - Items with Confidentiality / Integrity / Availability involvement (security needed)
A3: Ref | B3: Source | C3: Title | D3: Security requirement | E3: C | F3: I | G3: A | H3: Why CIA is involved / what must be protected | I3: ISO 27001:2022 cross-ref | J3: Evidence to verify | K3: Applicable (SoA) | L3: Status | M3: Owner | N3: Notes / Gap
A4: Clauses 4-10
A5: 6.1.2 | B5: Clause | C5: AI risk assessment | D5: Define and apply an AI risk assessment process: risk criteria, consistent/valid/comparable results, identify risks, analyse potential consequences and likelihood, evaluate and prioritise; retain documented information. | E5: ● | F5: ● | G5: ● | H5: Cover AI-specific threats: data poisoning, model theft/inversion, adversarial inputs, prompt injection, supply chain. | I5: 6.1.2, A.5.7 | J5: AI risk methodology, AI risk register and assessments | K5: Yes | L5: Not started
A6: 6.1.3 | B6: Clause | C6: AI risk treatment | D6: Define AI risk treatment process: select options, determine necessary controls (compare with Annex A), produce Statement of Applicability with justification, formulate treatment plan, obtain approval and residual risk acceptance. | E6: ● | F6: ● | G6: ● | H6: Select security controls; compare with ISO 27001 Annex A in SoA. | I6: 6.1.3 | J6: AI risk treatment plan, SoA, residual risk sign-off | K6: Yes | L6: Not started
A7: 7.5.3 | B7: Clause | C7: Control of documented information | D7: Control availability, protection, distribution, access, storage, version control, retention and disposition; control external-origin documents. | E7: ● | F7: ● | G7: ● | H7: Protect confidentiality/integrity/availability of AIMS documents (models, data docs). | I7: 7.5.3, A.5.33 | J7: DMS configuration, retention rules | K7: Yes | L7: Not started
A8: 8.2 | B8: Clause | C8: AI risk assessment | D8: Perform AI risk assessments at planned intervals or when significant changes are proposed/occur; retain results. | E8: ● | F8: ● | G8: ● | H8: Periodic AI security risk assessment. | I8: 8.2 | J8: Dated risk assessment outputs | K8: Yes | L8: Not started
A9: 8.3 | B9: Clause | C9: AI risk treatment | D9: Implement the AI risk treatment plan and retain results of treatment. | E9: ● | F9: ● | G9: ● | H9: Implement security risk treatment plan. | I9: 8.3 | J9: Treatment plan status, closure evidence | K9: Yes | L9: Not started
A10: Annex A controls
A11: A.4.4 | B11: Annex A | C11: Tooling resources | D11: Document tooling resources used for the AI system (algorithms, models, libraries, frameworks, MLOps). | E11: ● | F11: ● | G11: ● | H11: Secure AI libraries, frameworks, model artifacts, MLOps pipeline. | I11: A.5.21, A.8.9, A.8.19, A.8.30 | J11: Tooling/model registry, SBOM/MLBOM | K11: Yes | L11: Not started
A12: A.4.5 | B12: Annex A | C12: System and computing resources | D12: Document system and computing resources used (hardware, cloud, compute, storage). | E12: ● | F12: ● | G12: ● | H12: Secure compute, cloud and GPU/infrastructure. | I12: A.5.23, A.8.6, A.8.9, A.8.20, A.7.8 | J12: Infrastructure/compute inventory | K12: Yes | L12: Not started
A13: A.6.1.3 | B13: Annex A | C13: Processes for responsible AI system design and development | D13: Define and document specific processes for responsible design and development of AI systems. | E13: ● | F13: ● | G13: ● | H13: Secure-by-design AI SDLC. | I13: A.8.25, A.8.27, A.8.28 | J13: AI SDLC/MLOps procedures, gates | K13: Yes | L13: Not started
A14: A.6.2.2 | B14: Annex A | C14: AI system requirements and specification | D14: Specify and document requirements for new AI systems or material enhancements. | E14: ● | F14: ● | G14: ● | H14: Security requirements and threat modelling for AI. | I14: A.8.26, A.8.27, A.5.8 | J14: Requirements specs incl. risk/impact inputs | K14: Yes | L14: Not started
A15: A.6.2.4 | B15: Annex A | C15: AI system verification and validation | D15: Define and document verification/validation measures and criteria (performance, bias, robustness, security testing). | E15: ● | F15: ● | G15: ● | H15: Adversarial/red-team testing, robustness, vulnerability scanning. | I15: A.8.29, A.8.8, A.8.33 | J15: Test plans, V&V reports, acceptance criteria | K15: Yes | L15: Not started
A16: A.6.2.5 | B16: Annex A | C16: AI system deployment | D16: Document a deployment plan and ensure appropriate requirements are met before deployment. | F16: ● | G16: ● | H16: Secure release, change approval, environment separation. | I16: A.8.32, A.8.31, A.8.9 | J16: Deployment plan, go-live approval | K16: Yes | L16: Not started
A17: A.6.2.6 | B17: Annex A | C17: AI system operation and monitoring | D17: Define and document elements for ongoing operation: system and performance monitoring, repairs, updates and support. | E17: ● | F17: ● | G17: ● | H17: Drift/abuse monitoring, patching, incident detection. | I17: A.8.15, A.8.16, A.8.8, A.5.25 | J17: Monitoring dashboards, drift/performance alerts, update procedures | K17: Yes | L17: Not started
A18: A.6.2.8 | B18: Annex A | C18: AI system recording of event logs | D18: Determine at which phases of the life cycle event logs should be enabled, at minimum when the system is in use. | E18: ● | F18: ● | H18: Tamper-resistant logs, time sync, retention. | I18: A.8.15, A.8.16, A.8.17 | J18: Logging standard, log samples, retention | K18: Yes | L18: Not started
A19: A.7.4 | B19: Annex A | C19: Quality of data for AI systems | D19: Define and document data quality requirements and ensure data used meets them. | F19: ● | H19: Data integrity; defence against poisoning. | I19: A.5.12 | J19: Data quality criteria and check results | K19: Yes | L19: Not started
A20: A.7.5 | B20: Annex A | C20: Data provenance | D20: Define and document a process for recording provenance of data (and its updates) throughout the life cycle. | F20: ● | H20: Traceability and integrity of data lineage. | I20: A.5.9, A.8.15, A.5.33 | J20: Lineage/provenance records | K20: Yes | L20: Not started
A21: A.8.4 | B21: Annex A | C21: Communication of incidents | D21: Determine and document a plan for communicating incidents to users and other interested parties (incl. regulators). | E21: ● | F21: ● | G21: ● | H21: Incident notification to users/regulators. | I21: A.5.24, A.5.26, A.5.5 | J21: AI incident communication plan | K21: Yes | L21: Not started
A22: A.10.2 | B22: Annex A | C22: Allocating responsibilities | D22: Ensure responsibilities within the AI life cycle are allocated between the organization, partners, suppliers, customers and third parties. | E22: ● | F22: ● | G22: ● | H22: Shared-responsibility for security across parties. | I22: A.5.19, A.5.20, A.5.23 | J22: Responsibility matrix, contracts | K22: Yes | L22: Not started
A23: A.10.3 | B23: Annex A | C23: Suppliers | D23: Establish a process to ensure supplier services, products or materials align with the organization's responsible AI approach. | E23: ● | F23: ● | G23: ● | H23: Supplier security due diligence, contracts, monitoring. | I23: A.5.19-A.5.22 | J23: Supplier AI due-diligence, contract clauses | K23: Yes | L23: Not started

Sheet 2 Non-CIA (Other) Controls
A1: ISO/IEC 42001:2023 - Remaining items (governance, ethics, societal, privacy, documentation - no direct CIA protection)
A3: Ref | B3: Source | C3: Title | D3: Requirement | E3: Nature of requirement | F3: Security enabler link (indirect, if any) | G3: Evidence to verify | H3: Applicable (SoA) | I3: Status | J3: Owner | K3: Notes / Gap
A4: Clauses 4-10
A5: 4.1 | B5: Clause | C5: Understanding the organization and its context | D5: Determine external/internal issues relevant to the AIMS purpose and to achieving its intended results, incl. the organization's role(s) (provider, producer, user, etc.) and applicable AI-related climate/regulatory factors. | E5: Governance & context | F5: Include threat landscape/AI attack surface in context. (4.1) | G5: Context analysis, AI role determination, issue register | H5: Yes | I5: Not started
A6: 4.2 | B6: Clause | C6: Understanding the needs and expectations of interested parties | D6: Identify interested parties relevant to the AIMS, their requirements (incl. legal/regulatory, e.g. EU AI Act, PDPPL) and which will be addressed through the AIMS. | E6: Governance & context | F6: Security, privacy and regulatory requirements of stakeholders. (4.2) | G6: Stakeholder register, AI regulatory/contractual requirements register | H6: Yes | I6: Not started
A7: 4.3 | B7: Clause | C7: Determining the scope of the AI management system | D7: Determine and document AIMS boundaries and applicability, considering 4.1, 4.2 and the AI systems in scope. | E7: Governance & context | F7: Scope should cover AI assets and their security boundaries. (4.3) | G7: Approved AIMS scope statement, AI system list | H7: Yes | I7: Not started
A8: 4.4 | B8: Clause | C8: AI management system | D8: Establish, implement, maintain and continually improve the AIMS, including needed processes and their interactions. | E8: Governance & context | F8: Integrate AIMS with the ISMS. (4.4) | G8: AIMS process map/manual | H8: Yes | I8: Not started
A9: 5.1 | B9: Clause | C9: Leadership and commitment | D9: Top management demonstrates commitment: AI policy and objectives aligned to strategy, AIMS integrated into processes, resources provided, importance of effective AI management communicated, outcomes ensured, improvement promoted. | E9: Leadership & governance | F9: Leadership commitment to security within AI governance. (5.1) | G9: Management minutes, sponsorship, budget approvals | H9: Yes | I9: Not started
A10: 5.2 | B10: Clause | C10: AI policy | D10: Establish, document, communicate and make available an AI policy appropriate to the organization's purpose, providing a framework for AI objectives, committing to applicable requirements and continual improvement; consistent with other policies. | E10: Leadership & governance | F10: AI policy must align with the information security policy. (5.2, A.5.1) | G10: Approved AI policy, communication records | H10: Yes | I10: Not started
A11: 5.3 | B11: Clause | C11: Roles, responsibilities and authorities | D11: Assign and communicate AIMS roles, incl. responsibility for conformity to the standard and reporting AIMS performance to top management. | E11: Leadership & governance | F11: Security roles for AI systems. (5.3, A.5.2) | G11: RACI, AI governance charter, appointment records | H11: Yes | I11: Not started
A12: 6.1.1 | B12: Clause | C12: Actions to address risks and opportunities - General | D12: Determine risks and opportunities to give assurance the AIMS achieves outcomes, prevents/reduces undesired effects, and enables improvement; plan actions and evaluate effectiveness. | E12: Risk & planning (general) | F12: Security risks/opportunities feed AIMS planning. (6.1.1) | G12: Risk & opportunity register | H12: Yes | I12: Not started
A13: 6.1.4 | B13: Clause | C13: AI system impact assessment | D13: Define a process to assess potential consequences of AI systems on individuals, groups and society through their life cycle; document and retain results. | E13: Impact assessment (individual / societal) | F13: Impacts from security failures (privacy breach, safety harm). (A.5.34) | G13: Impact assessment procedure and completed assessments | H13: Yes | I13: Not started
A14: 6.2 | B14: Clause | C14: AI objectives and planning to achieve them | D14: Establish measurable AI objectives at relevant functions/levels, consistent with the AI policy; plan what, resources, owner, deadline and evaluation. | E14: Risk & planning (general) | F14: Set security/robustness objectives for AI systems. (6.2) | G14: AI objectives register, KPIs | H14: Yes | I14: Not started
A15: 6.3 | B15: Clause | C15: Planning of changes | D15: Carry out AIMS changes in a planned manner when a need for change is determined. | E15: Risk & planning (general) | F15: Security review of AIMS/AI system changes. (6.3, A.8.32) | G15: Change records, impact analysis | H15: Yes | I15: Not started
A16: 7.1 | B16: Clause | C16: Resources | D16: Determine and provide resources needed to establish, implement, maintain and improve the AIMS. | E16: Support: resources, competence, communication | F16: None | G16: Resource plans, budget | H16: Yes | I16: Not started
... A31: 10.2 | B31: Clause | C31: Nonconformity and corrective action | D31: React to NCs, evaluate need to eliminate causes, implement and review corrective action effectiveness, update AIMS; retain evidence. | E31: Improvement | F31: Corrective action after security incidents/NCs. (10.2, A.5.27) | G31: NC/CAPA log, root-cause analyses | H31: Yes | I31: Not started
A32: Annex A controls
A33: A.2.2 | B33: Annex A | C33: AI policy | D33: Document a policy for the development or use of AI systems. | E33: AI policy & alignment | F33: Reference security requirements in AI policy. (A.5.1) | G33: Approved AI policy | H33: Yes | I33: Not started
A34: A.2.3 | B34: Annex A | C34: Alignment with other organizational policies | D34: Determine where other policies (security, privacy, quality, safety, etc.) are affected by or apply to AI objectives, and align them. | E34: AI policy & alignment | F34: Align with information security and privacy policies. (A.5.1) | G34: Policy mapping/crosswalk | H34: Yes | I34: Not started
A35: A.2.4 | B35: Annex A | C35: Review of the AI policy | D35: Review the AI policy at planned intervals or on significant change to ensure continuing suitability, adequacy and effectiveness. | E35: AI policy & alignment | F35: None | G35: Review records, version history | H35: Yes | I35: Not started
A36: A.3.2 | B36: Annex A | C36: AI roles and responsibilities | D36: Define and allocate AI roles and responsibilities per organizational needs. | E36: Organization & accountability | F36: Security accountability for AI systems. (A.5.2, A.5.4) | G36: AI governance roles, RACI, committee charter | H36: Yes | I36: Not started
A37: A.3.3 | B37: Annex A | C37: Reporting of concerns | D37: Define and put in place a process to report concerns about the organization's role with respect to an AI system throughout its life cycle. | E37: Organization & accountability | F37: Channel for security concerns. (A.6.8, A.5.26) | G37: Whistleblowing/concern channel, case records | H37: Yes | I37: Not started
A38: A.4.2 | B38: Annex A | C38: Resource documentation | D38: Identify and document relevant resources required for each AI system life-cycle stage and other AI-related activities, to understand and address risks/impacts. | E38: AI resource management | F38: Asset inventory of AI resources. (A.5.9) | G38: AI resource inventory | H38: Yes | I38: Not started
A39: A.4.3 | B39: Annex A | C39: Data resources | D39: Document information about data resources used for the AI system. | E39: AI resource management | F39: Classification and protection of datasets. (A.5.9, A.5.12) | G39: Dataset inventory, data catalogue | H39: Yes | I39: Not started
A40: A.4.6 | B40: Annex A | C40: Human resources | D40: Document human resources and their competences for development, deployment, operation, change management, maintenance, transfer and decommissioning, and verification and integration of the AI system. | E40: AI resource management | F40: Vetted, trained AI personnel. (A.6.1, A.6.3) | G40: Competence matrix, staffing records | H40: Yes | I40: Not started
A41: A.5.2 | B41: Annex A | C41: AI system impact assessment process | D41: Establish a process to assess potential consequences for individuals, groups and society from the AI system throughout its life cycle. | E41: Impact assessment (individual / societal) | F41: Include security and privacy harms in impact process. (A.5.34) | G41: Impact assessment procedure and triggers | H41: Yes | I41: Not started
A42: A.5.3 | B42: Annex A | C42: Documentation of AI system impact assessments | D42: Document results of impact assessments and retain for a defined period. | E42: Impact assessment (individual / societal) | F42: None | G42: Assessment records and retention rules | H42: Yes | I42: Not started
A43: A.5.4 | B43: Annex A | C43: Assessing AI system impact on individuals or groups of individuals | D43: Assess and document impacts on individuals/groups throughout the life cycle (e.g. fairness, privacy, safety, rights). | E43: Impact assessment (individual / societal) | F43: Privacy/safety impacts on individuals. (A.5.34) | G43: Individual/group impact analyses, fairness testing | H43: Yes | I43: Not started
A44: A.5.5 | B44: Annex A | C44: Assessing societal impacts of AI systems | D44: Assess and document societal impacts (e.g. environment, economy, culture, public health, misinformation) throughout the life cycle. | E44: Impact assessment (individual / societal) | F44: None | G44: Societal impact analyses | H44: Yes | I44: Not started
... A57: A.10.4 | B57: Annex A | C57: Customers | D57: Ensure the organization's responsible AI approach considers customer expectations and needs. | E57: Customer relationships | F57: Customer security and data requirements. (A.5.20, A.5.34) | G57: Customer requirements, feedback, contractual commitments | H57: Yes | I57: Not started

Sheet 3 EU AI Act
A1: EU AI Act (Regulation (EU) 2024/1689) - Clause Checklist, with Role Responsibilities and CIA-Security Marking
A2: Role Legend (Article 3 definitions)
A3: Role | B3: Definition (Art.3) | C3: Key responsibilities (summary)
A4: Provider | B4: Develops an AI system or GPAI model (or has one developed) and places it on the market / puts it into service under its own name or trademark, for payment or free of charge. | C4: Bears the primary compliance burden: classification, risk management, technical documentation, conformity assessment, CE marking, registration, post-market monitoring, incident reporting.
A5: Deployer | B5: Uses an AI system under its own authority, except where used in the course of a purely personal, non-professional activity. | C5: Must use the system per the provider's instructions, assign competent human oversight, monitor operation, keep logs it controls, and report risks/incidents it becomes aware of.
A6: Authorised Representative | B6: A person established in the EU, holding a written mandate from a non-EU provider, to act on the provider's behalf for specified obligations. | C6: Carries out mandated tasks (conformity documentation, registration, cooperation with authorities) on behalf of a non-EU provider.
A7: Importer | B7: A person established in the EU that places on the EU market an AI system bearing the name or trademark of a person established outside the EU. | C7: Verifies conformity assessment, documentation and CE marking before placing the system on the market; ensures safe storage/transport.
A8: Distributor | B8: A person in the supply chain, other than the provider or importer, that makes an AI system available on the EU market. | C8: Verifies CE marking and documentation before distribution; must not distribute non-conforming systems; takes corrective action if non-conformity is found.
A9: Product Manufacturer | B9: Places an AI system on the market or into service together with its own product, under its own name or trademark. | C9: Takes on provider-equivalent obligations for the AI system embedded in its product.
A10: Operator (umbrella term) | B10: Collective term covering Provider, Deployer, Authorised Representative, Importer, Distributor and Product Manufacturer. | C10: Used where an obligation (e.g. Art.5 prohibited practices, Art.99 penalties) applies across all roles rather than one specifically.
A11: GPAI Model Provider | B11: A Provider specifically of a general-purpose AI model; a further 'systemic risk' tier applies above a compute/capability threshold (Art.51). | C11: Technical documentation, downstream-provider information, copyright policy, training-content summary (Art.53); systemic-risk providers add model evaluation, adversarial testing and cybersecurity protection (Art.55).
A13: Article/Annex | B13: Title | C13: Applicable Role(s) & Responsibilities | D13: Requirement | E13: C | F13: I | G13: A | H13: Security note / why CIA is involved | I13: Evidence to verify | J13: Applicable | K13: Status | L13: Owner | M13: Notes / Gap
A14: Chapter I | B14: General provisions
A15: Art.2 | B15: Scope | C15: Operator (umbrella term covering Provider, Deployer, Importer, Distributor, Authorised Representative, Product Manufacturer) - this article determines which role(s) an organization holds and therefore which obligations apply. | D15: Determine applicability: providers, deployers, importers, distributors and product manufacturers placing AI systems/GPAI models on the EU market or whose output is used in the EU. | H15: None - governance/process requirement without a direct CIA-protection function. | I15: Applicability assessment | J15: Yes | K15: Not started
A16: Art.3 | B16: Definitions | C16: All roles - this article is the source of the role definitions themselves (see the Role Legend above). | D16: Apply the Act's definitions (AI system, provider, deployer, high-risk, GPAI model, serious incident, etc.) consistently across governance documents. | H16: None - governance/process requirement without a direct CIA-protection function. | I16: Glossary/definitions mapping | J16: Yes | K16: Not started
A17: Art.4 | B17: AI literacy | C17: Provider and Deployer - both must ensure their own staff (and others acting on their behalf) have sufficient AI literacy. | D17: Take measures to ensure sufficient AI literacy of staff and others dealing with AI systems on the organization's behalf, considering their technical knowledge, experience and context of use. | H17: None - governance/process requirement without a direct CIA-protection function. | I17: AI literacy programme, training records | J17: Yes | K17: Not started
A18: Chapter II | B18: Prohibited AI practices
A19: Art.5 | B19: Prohibited AI practices | C19: Provider (must not place on market/put into service) and Deployer (must not use) - the prohibition binds both roles independently. | D19: Do not place on the market, put into service or use AI systems for prohibited practices: subliminal/manipulative techniques causing harm, exploitation of vulnerabilities, social scoring, real-time remote biometric ID in public for law enforcement (subject to exceptions), biometric categorisation inferring sensitive attributes, emotion recognition in workplace/education (with exceptions), untargeted facial-image scraping, individual crime-risk prediction based solely on profiling. | E19: ● | H19: Emotion recognition, biometric categorisation and scraping controls overlap with data confidentiality and consent safeguards. | I19: Prohibited-use screening/legal review, use-case register | J19: Yes | K19: Not started
A20: Chapter III S1 | B20: High-risk classification
A21: Art.6 | B21: Classification rules for high-risk AI systems | C21: Provider - responsible for classifying their own AI system before placing it on the market or putting it into service. | D21: Determine whether an AI system is high-risk: safety component of a regulated product (Annex I) or use case listed in Annex III, with a narrow self-assessment exemption where risk is not significant. | H21: None - governance/process requirement without a direct CIA-protection function. | I21: Classification/risk-tier assessment per system | J21: Yes | K21: Not started
A22: Art.7 | B22: Amendments to Annex III | C22: Provider - must monitor for classification-list changes affecting systems it has already placed on the market. | D22: Monitor Commission updates to the high-risk use-case list (Annex III) and re-assess systems accordingly. | H22: None - governance/process requirement without a direct CIA-protection function. | I22: Regulatory watch process | J22: Yes | K22: Not started
A23: Chapter III S2 | B23: Requirements for high-risk AI systems
A24: Art.8 | B24: Compliance with the requirements | C24: Provider - primary and direct responsibility for meeting Articles 9-15 across the system's lifecycle. | D24: Ensure high-risk AI systems comply with Articles 9-15 throughout their lifecycle, considering intended purpose and generally acknowledged state of the art. | H24: None - governance/process requirement without a direct CIA-protection function. | I24: Compliance programme covering Art.9-15 | J24: Yes | K24: Not started
A25: Art.9 | B25: Risk management system | C25: Provider - must establish and maintain the risk management system for the high-risk AI system. | D25: Establish, implement, document and maintain a continuous risk management process across the lifecycle: identify, analyse, estimate and evaluate known/foreseeable risks, adopt mitigation measures, and test. | F25: ● | H25: Risk management must cover security/adversarial risks alongside safety and fundamental-rights risks. | I25: AI risk management file, test reports | J25: Yes | K25: Not started
A26: Art.10 | B26: Data and data governance | C26: Provider - responsible for the data governance practices applied during development of the high-risk AI system. | D26: Apply data governance practices to training/validation/testing data: relevant design choices, provenance, collection, bias examination, gaps identification, and appropriate quality/representativeness; protect data appropriately. | E26: ● | F26: ● | H26: Poor data governance is a direct integrity risk (poisoning, bias) and can expose confidential data if provenance/access is not controlled. | I26: Data governance procedure, dataset documentation | J26: Yes | K26: Not started
A27: Art.11 | B27: Technical documentation | C27: Provider - must draw up and maintain the technical documentation per Annex IV. | D27: Draw up technical documentation before placing on the market/putting into service and keep it up to date, per Annex IV (system description, design, development, risk management, performance, changes). | H27: None - governance/process requirement without a direct CIA-protection function. | I27: Technical documentation file | J27: Yes | K27: Not started
A28: Art.12 | B28: Record-keeping (logging) | C28: Provider - must design the logging capability into the system; Deployer - relies on and operates these logs during use (see Art.26). | D28: Design high-risk AI systems with capability for automatic logging of events over the system's lifetime to ensure traceability appropriate to intended purpose. | F28: ● | G28: ● | H28: Tamper-evident, available logs are needed for traceability and incident investigation. | I28: Logging design spec, log retention records | J28: Yes | K28: Not started
A29: Art.13 | B29: Transparency and provision of information to deployers | C29: Provider - must design for transparency and supply instructions for use; Deployer - is the recipient of this information and relies on it for compliant use. | D29: Design systems to be sufficiently transparent for deployers to interpret output and use appropriately; provide instructions for use with required content (identity, characteristics, performance, known limitations, human oversight measures, expected lifetime and maintenance). | H29: None - governance/process requirement without a direct CIA-protection function. | I29: Instructions for use, transparency documentation | J29: Yes | K29: Not started
A30: Art.14 | B30: Human oversight | C30: Provider - must design the human-oversight interface/tools into the system; Deployer - must actually assign competent human oversight during use (see Art.26). | D30: Design high-risk AI systems, including appropriate human-machine interface tools, to be effectively overseen by natural persons during use, able to understand, monitor and intervene (incl. stop/override). | H30: None - governance/process requirement without a direct CIA-protection function. | I30: Human oversight design, operator training | J30: Yes | K30: Not started
A31: Art.15 | B31: Accuracy, robustness and cybersecurity | C31: Provider - sole responsibility for designing and testing accuracy, robustness and cybersecurity into the system. | D31: Design and develop high-risk AI systems to achieve appropriate levels of accuracy, robustness and cybersecurity, perform consistently, and be resilient to errors, faults, inconsistencies, and attempts by unauthorised third parties to exploit vulnerabilities (data poisoning, adversarial examples, model evasion, confidentiality attacks), with technical redundancy/back-up where relevant. | E31: ● | F31: ● | G31: ● | H31: Direct cybersecurity obligation: protect against attacks on confidentiality (model/data extraction), integrity (poisoning, adversarial manipulation) and availability (denial of service, faults). | I31: Robustness/security test reports, resilience measures, cybersecurity controls | J31: Yes | K31: Not started
A32: Chapter III S3 | B32: Provider/deployer obligations
A33: Art.16 | B33: Obligations of providers of high-risk AI systems | C33: Provider - this article consolidates the full set of provider-specific obligations. | D33: Ensure conformity, have quality management system, keep documentation/logs, undergo conformity assessment, draw up EU declaration of conformity, affix CE marking, register system, take corrective action, cooperate with authorities. | H33: None - governance/process requirement without a direct CIA-protection function. | I33: Conformity file, CE marking, registration | J33: Yes | K33: Not started
A34: Art.17 | B34: Quality management system | C34: Provider - must establish and maintain the QMS. | D34: Put in place a quality management system documenting strategy for compliance, design control, data management, risk management, post-market monitoring, incident reporting, resource management, and an accountability framework. | H34: None - governance/process requirement without a direct CIA-protection function. | I34: QMS documentation | J34: Yes | K34: Not started
A35: Art.18 | B35: Documentation keeping | C35: Provider - the 10-year document retention duty rests with the provider. | D35: Keep technical documentation, QMS documentation, conformity assessment and EU declaration of conformity documentation for 10 years after placing on the market. | H35: None - governance/process requirement without a direct CIA-protection function. | I35: Document retention register | J35: Yes | K35: Not started
A36: Art.19 | B36: Automatically generated logs | C36: Provider - retains logs that are under its control (contrast with Art.26, where the Deployer retains logs under its own control). | D36: Keep the logs automatically generated by the high-risk AI system, to the extent they are under the provider's control, for a period appropriate to the intended purpose (at least 6 months unless otherwise provided). | F36: ● | G36: ● | H36: Preserving log integrity and availability for the retention period. | I36: Log retention policy and records | J36: Yes | K36: Not started
A37: Art.20 | B37: Corrective actions and duty of information | C37: Provider - must act and must notify Distributors, Deployers, the Authorised Representative and authorities as relevant. | D37: Take corrective actions or withdraw/recall a non-conforming system; inform distributors, deployers, authorised representative and, where relevant, authorities of the non-conformity and actions taken. | H37: None - governance/process requirement without a direct CIA-protection function. | I37: Corrective action procedure, notifications | J37: Yes | K37: Not started
A38: Art.21 | B38: Cooperation with competent authorities | C38: Provider - primary duty to cooperate; an Authorised Representative may also be approached where the provider is outside the EU. | D38: Provide competent authorities, on reasoned request, with information/documentation to demonstrate conformity, including access to automatically generated logs where relevant. | E38: ● | H38: Ensure controlled, confidential handling of information shared with authorities. | I38: Authority request-response log | J38: Yes | K38: Not started
A39: Art.22 | B39: Authorised representatives | C39: Authorised Representative - this article defines its role and mandated duties, appointed by a non-EU Provider. | D39: Non-EU providers appoint an EU authorised representative with a mandate covering conformity documentation, cooperation with authorities and registration duties. | H39: None - governance/process requirement without a direct CIA-protection function. | I39: Authorisation mandate | J39: Yes | K39: Not started
A40: Art.23 | B40: Obligations of importers | C40: Importer - this article sets out the Importer's specific verification and cooperation duties. | D40: Verify conformity assessment, documentation and CE marking before placing a system on the market; ensure storage/transport conditions do not jeopardise compliance; cooperate with authorities. | H40: None - governance/process requirement without a direct CIA-protection function. | I40: Import verification records | J40: Yes | K40: Not started
A41: Art.24 | B41: Obligations of distributors | C41: Distributor - this article sets out the Distributor's specific verification duties. | D41: Verify CE marking, documentation and conformity before making a system available; not make available if non-conforming; take corrective action if aware of non-conformity. | H41: None - governance/process requirement without a direct CIA-protection function. | I41: Distribution verification records | J41: Yes | K41: Not started
A42: Art.25 | B42: Responsibilities along the AI value chain | C42: Distributor, Importer, Deployer or third-party supplier - any of these can be re-classified as a Provider under the stated conditions and then assumes full Provider obligations. | D42: Determine when a distributor, importer, deployer or third party is considered a provider (e.g. substantial modification, own branding) and assumes provider obligations; third-party suppliers provide necessary information/access via written agreement. | E42: ● | H42: Agreements should protect confidentiality of shared IP/technical information. | I42: Value-chain responsibility agreements | J42: Yes | K42: Not started
A43: Art.26 | B43: Obligations of deployers of high-risk AI systems | C43: Deployer - this article consolidates the full set of deployer-specific obligations, the mirror of Art.16 for providers. | D43: Use systems per instructions, assign competent human oversight, ensure input data relevance, monitor operation, keep automatically generated logs (min. 6 months), inform provider/authorities of risks or serious incidents, cooperate with authorities, conduct data protection impact assessment where applicable. | F43: ● | G43: ● | H43: Deployer must protect and retain logs and monitor for security-relevant anomalies. | I43: Deployer operating procedures, log retention, DPIA | J43: Yes | K43: Not started
A44: Art.27 | B44: Fundamental rights impact assessment | C44: Deployer - specifically deployers that are public bodies or private entities providing public services, or operating in banking/insurance, per the article's scope. | D44: Certain deployers (public bodies, banking/insurance, etc.) perform a fundamental rights impact assessment before deployment: process description, period/frequency of use, affected persons, specific risks, human oversight measures, and mitigation/governance measures. | H44: None - governance/process requirement without a direct CIA-protection function. | I44: FRIA report | J44: Yes | K44: Not started
A45: Chapter V | B45: General-purpose AI models
A46: Art.53 | B46: Obligations for providers of GPAI models | C46: GPAI Model Provider - a provider specifically of a general-purpose AI model (distinct from, but can overlap with, a high-risk AI system Provider). | D46: Draw up and keep up to date technical documentation, provide information/documentation to downstream providers, establish a copyright policy, publish a sufficiently detailed training-content summary. | H46: None - governance/process requirement without a direct CIA-protection function. | I46: GPAI technical documentation, training data summary | J46: Yes | K46: Not started
A47: Art.55 | B47: Obligations for providers of GPAI models with systemic risk | C47: GPAI Model Provider meeting the systemic-risk threshold (based on compute/capability criteria) - an elevated obligation tier on top of Art.53. | D47: Perform model evaluation incl. adversarial testing, assess and mitigate systemic risks, track/document/report serious incidents, ensure adequate cybersecurity protection for the model and its physical infrastructure. | E47: ● | F47: ● | G47: ● | H47: Explicit cybersecurity protection obligation for the model and infrastructure against theft, unauthorized access and attacks. | I47: Systemic risk assessment, adversarial test reports, incident log, cybersecurity measures | J47: Yes | K47: Not started
A48: Chapter VIII | B48: Transparency obligations
A49: Art.50 | B49: Transparency obligations for certain AI systems | C49: Provider (must design the disclosure/labelling capability into the system) and Deployer (must make the actual disclosure to natural persons at the point of interaction/use). | D49: Inform natural persons they are interacting with an AI system (unless obvious); mark synthetic audio/image/video/text (deepfakes) as AI-generated/manipulated; disclose AI-generated text on matters of public interest; disclose emotion-recognition/biometric-categorisation use to exposed persons. | H49: None - governance/process requirement without a direct CIA-protection function. | I49: Disclosure notices, watermarking/labelling mechanism | J49: Yes | K49: Not started
A50: Chapter IX | B50: Post-market monitoring and incident reporting
A51: Art.72 | B51: Post-market monitoring by providers | C51: Provider - must establish and operate the post-market monitoring system. | D51: Establish and document a post-market monitoring system proportionate to the AI technology and risks, actively/systematically collecting and analysing performance data throughout the system's lifetime. | F51: ● | G51: ● | H51: Monitoring must detect performance degradation and security-relevant anomalies over time. | I51: Post-market monitoring plan and records | J51: Yes | K51: Not started
A52: Art.73 | B52: Reporting of serious incidents | C52: Provider - primary reporting duty; Deployer - must also inform the Provider (or importer/distributor) and relevant authorities of any serious incident it identifies (per Art.26). | D52: Report serious incidents involving high-risk AI systems to market surveillance authorities without undue delay (specified timelines, incl. immediate for widespread infringement/critical infrastructure), investigate and take corrective action. | E52: ● | F52: ● | G52: ● | H52: Security incidents affecting the AI system fall within serious-incident reporting duties. | I52: Incident reporting procedure, incident register | J52: Yes | K52: Not started
A53: Chapter XII | B53: Penalties
A54: Art.99 | B54: Penalties | C54: All roles (Provider, Deployer, Importer, Distributor, Authorised Representative, GPAI Provider) - penalties apply to whichever role is found non-compliant with its specific obligations. | D54: Ensure compliance to avoid administrative fines (tiered by severity, up to the higher of EUR 35m or 7% of global turnover for prohibited-practice breaches). | H54: None - governance/process requirement without a direct CIA-protection function. | I54: Compliance/legal risk register | J54: Yes | K54: Not started
A55: Annex III | B55: High-risk AI system use cases | C55: Provider - uses this annex to classify its system (Art.6); Deployer - should also be aware of it, particularly public-sector and essential-services deployers subject to Art.27 FRIA. | D55: Check whether the AI system falls under a listed high-risk use case (biometrics, critical infrastructure, education, employment, essential services incl. access to insurance/credit, law enforcement, migration/asylum/border, justice/democratic processes). | H55: None - governance/process requirement without a direct CIA-protection function. | I55: Use-case mapping against Annex III | J55: Yes | K55: Not started
A56: Annex IV | B56: Technical documentation content | C56: Provider - sole responsibility for producing technical documentation to this content standard (Art.11). | D56: Ensure technical documentation covers general description, design/development process and choices, monitoring/functioning/control, risk management measures, lifecycle changes, standards applied, and EU declaration of conformity. | H56: None - governance/process requirement without a direct CIA-protection function. | I56: Technical documentation checklist | J56: Yes | K56: Not started

Sheet 4 OECD AI Principles
A1: OECD AI Principles (Recommendation of the Council on AI, updated May 2024) - Checklist, with CIA-Security Marking
A3: Ref | B3: Title | C3: Requirement | D3: C | E3: I | F3: A | G3: Security note / why CIA is involved | H3: Evidence to verify | I3: Applicable | J3: Status | K3: Owner | L3: Notes / Gap
A4: Section 1 | B4: Values-based principles for trustworthy AI
A5: 1.1 | B5: Inclusive growth, sustainable development and well-being | C5: AI actors should proactively engage in responsible stewardship of trustworthy AI for beneficial outcomes: augmenting human capabilities, advancing inclusion of underrepresented populations, reducing inequalities, and protecting the environment. | G5: None - governance/policy-level recommendation. | H5: Responsible-AI stewardship programme, sustainability/inclusion assessment | I5: Yes | J5: Not started
A6: 1.2 | B6: Human rights, democratic values and fairness (incl. privacy) | C6: Respect the rule of law, human rights and democratic values throughout the AI system lifecycle: non-discrimination, equality, freedom, dignity, autonomy, privacy and data protection, diversity, fairness, social justice and labour rights; implement mechanisms such as human oversight where needed. | D6: ● | G6: Privacy and data protection require confidentiality controls over personal data used by AI systems. | H6: Fairness/bias testing, privacy impact assessment, human oversight design | I6: Yes | J6: Not started
A7: 1.3 | B7: Transparency and explainability | C7: AI actors should provide meaningful information appropriate to context: to foster understanding, inform of AI interaction, enable those affected to understand outcomes, and enable those adversely affected to challenge outcomes based on plain and easy-to-understand information on factors and logic. | G7: None - governance/policy-level recommendation. | H7: Transparency notices, explainability documentation | I7: Yes | J7: Not started
A8: 1.4 | B8: Robustness, security and safety | C8: AI systems should function appropriately and not pose unreasonable safety/security risks throughout their lifecycle; traceability of datasets, processes and decisions; risk-based approach with continuous risk management (security, safety, bias) applied by AI actors to each phase; safeguards to ensure control can be reasserted (e.g. deactivation) when risks materialize. | D8: ● | E8: ● | F8: ● | G8: Directly requires security throughout the lifecycle: resilience against attacks, traceability (integrity), safe operation (availability/safety) and the ability to disable a malfunctioning or compromised system. | H8: Robustness/security testing, risk management process, traceability records, deactivation/kill-switch controls | I8: Yes | J8: Not started
A9: 1.5 | B9: Accountability | C9: AI actors should be accountable for the proper functioning of AI systems and respect of the principles, based on their roles, context, and consistent with the state of the art; enable traceability, incl. logging, to analyse outcomes and responses to inquiry; apply a systematic risk management approach to each phase of the lifecycle on an ongoing basis. | E9: ● | F9: ● | G9: Traceability/logging for accountability protects integrity of the record and requires availability of logs for inquiry. | H9: Accountability framework, role assignment, logging and audit trail | I9: Yes | J9: Not started
A10: Section 2 | B10: Policy recommendations for governments (organizational relevance)
A11: 2.1 | B11: Investing in AI research and development | C11: Foster investment in R&D, incl. long-term public investment and encouragement of private investment, to spur innovation in trustworthy AI. | G11: None - governance/policy-level recommendation. | H11: R&D investment plan / innovation budget | I11: Yes | J11: Not started
A12: 2.2 | B12: Fostering an inclusive AI-enabling ecosystem | C12: Foster accessible AI ecosystems with digital infrastructure, technologies, mechanisms to share data and knowledge responsibly and share metrics to measure AI research/development/deployment/growth. | G12: None - governance/policy-level recommendation. | H12: Ecosystem participation, data-sharing agreements | I12: Yes | J12: Not started
A13: 2.3 | B13: Shaping an enabling interoperable governance and policy environment | C13: Promote a policy environment that supports agile transition from R&D to deployment, incl. mechanisms such as regulatory sandboxes to experiment with AI safely, and work towards interoperable governance frameworks. | G13: None - governance/policy-level recommendation. | H13: Regulatory sandbox participation, policy/standards mapping | I13: Yes | J13: Not started
A14: 2.4 | B14: Building human capacity and preparing for labour-market transformation | C14: Equip people with skills for AI, support workers in transitioning jobs affected by AI, and ensure protection of labour rights. | G14: None - governance/policy-level recommendation. | H14: Workforce reskilling programme, labour-impact assessment | I14: Yes | J14: Not started
A15: 2.5 | B15: International co-operation for trustworthy AI | C15: Actively co-operate across borders and sectors to advance responsible stewardship of trustworthy AI, incl. common understanding of AI actor obligations, interoperable governance, standards and metrics. | G15: None - governance/policy-level recommendation. | H15: Participation in international AI governance initiatives | I15: Yes | J15: Not started
A16: Section 3 | B16: 2024 update focus areas
A17: 3.1 | B17: General-purpose and generative AI risks | C17: Address risks specific to general-purpose/foundation and generative AI models, incl. safety, misuse and information-integrity risks (e.g. disinformation, deepfakes). | G17: None - governance/policy-level recommendation. | H17: GPAI/genAI risk assessment, content provenance/watermarking | I17: Yes | J17: Not started
A18: 3.2 | B18: Environmental footprint | C18: Consider and where possible measure/reduce the environmental footprint (energy, compute, resources) of AI systems across their lifecycle. | G18: None - governance/policy-level recommendation. | H18: Environmental impact tracking (compute/energy use) | I18: Yes | J18: Not started
A19: 3.3 | B19: Intellectual property rights | C19: Respect intellectual property rights, incl. in relation to training data and generated content. | G19: None - governance/policy-level recommendation. | H19: IP due-diligence, training-data licensing review | I19: Yes | J19: Not started
A20: 3.4 | B20: Multi-stakeholder co-operation on risk | C20: Engage multiple stakeholders (government, industry, civil society, academia, technical community) to manage AI risks and information integrity collaboratively. | G20: None - governance/policy-level recommendation. | H20: Multi-stakeholder engagement records | I20: Yes | J20: Not started

Sheet 5 NIST AI RMF
A1: NIST AI RMF 1.0 (NIST.AI.100-1) - Category Checklist, with CIA-Security Marking
A3: Ref | B3: Category outcome | C3: Suggested action | D3: C | E3: I | F3: A | G3: Security note / why CIA is involved | H3: Evidence to verify | I3: Applicable | J3: Status | K3: Owner | L3: Notes / Gap
A4: GOVERN | B4: GOVERN - policy, accountability and culture (cross-cutting; applies to the whole organization)
A5: Govern 1 | B5: Policies, processes, procedures and practices for mapping, measuring and managing AI risk are established, documented and effectively implemented, reflecting organizational risk tolerance. | C5: Establish AI risk-management policies/processes covering legal/regulatory requirements, and review/update them regularly. | G5: None - governance/process-level outcome. | H5: AI risk management policy, process documentation, review log | I5: Yes | J5: Not started
A6: Govern 2 | B6: Accountability structures are in place so appropriate teams and individuals are empowered, responsible and trained for mapping, measuring and managing AI risks. | C6: Assign clear roles/responsibilities for AI risk management and provide training. | G6: None - governance/process-level outcome. | H6: RACI, role descriptions, training records | I6: Yes | J6: Not started
A7: Govern 3 | B7: Workforce diversity, equity, inclusion and accessibility processes are prioritized, and organizational risk management supported by a diverse team. | C7: Ensure diverse, multidisciplinary teams involved in AI risk decisions. | G7: None - governance/process-level outcome. | H7: Team composition records | I7: Yes | J7: Not started
A8: Govern 4 | B8: Organizational teams are committed to a culture that considers and communicates AI risk. | C8: Foster risk-aware culture, incl. incentives, policies for documenting risks/tradeoffs, and processes for flagging risks. | G8: None - governance/process-level outcome. | H8: Risk-culture initiatives, internal reporting mechanisms | I8: Yes | J8: Not started
A9: Govern 5 | B9: Processes are in place for robust engagement with relevant AI actors (incl. external stakeholders and end users). | C9: Establish mechanisms to solicit and incorporate feedback from relevant AI actors. | G9: None - governance/process-level outcome. | H9: Stakeholder engagement plan, feedback records | I9: Yes | J9: Not started
A10: Govern 6 | B10: Policies and procedures are in place to address AI risks and benefits arising from third-party software/data/systems and other supply-chain issues. | C10: Establish third-party/AI supply-chain risk management processes, incl. contracts and due diligence. | D10: ● | G10: Third-party/supply-chain AI components (models, data, libraries) are a confidentiality risk vector requiring security due diligence, similar to ISO 27001 supplier controls. | H10: Third-party AI risk policy, vendor due-diligence records, contract clauses | I10: Yes | J10: Not started
A11: MAP | B11: MAP - context, categorization and impacts (system-level)
A12: Map 1 | B12: Context is established and understood: intended purpose, business value, risk tolerances, requirements, and impacted stakeholders identified. | C12: Document AI system context: purpose, users, requirements (incl. legal/regulatory and security requirements). | G12: None - governance/process-level outcome. | H12: Context/use-case documentation | I12: Yes | J12: Not started
A13: Map 2 | B13: Categorization of the AI system is performed, incl. specific tasks and methods used to implement them. | C13: Categorize the AI system by task, method (e.g. classification, generative), and risk level. | G13: None - governance/process-level outcome. | H13: System categorization record | I13: Yes | J13: Not started
A14: Map 3 | B14: AI capabilities, targeted usage, goals and expected benefits/costs are understood compared with appropriate benchmarks. | C14: Document expected AI system performance and benchmarks; consider failure/edge cases. | G14: None - governance/process-level outcome. | H14: Benchmarking documentation, cost-benefit analysis | I14: Yes | J14: Not started
A15: Map 4 | B15: Risks and benefits are mapped for all components of the AI system, incl. third-party software, data and other supply-chain elements. | C15: Identify and document risks/benefits of each AI system component, incl. third-party/open-source elements. | D15: ● | E15: ● | F15: ● | G15: Mapping risks of models/data/components from the supply chain is core to protecting confidentiality, integrity and availability of the system. | H15: Component risk mapping, SBOM/data lineage | I15: Yes | J15: Not started
A16: Map 5 | B16: Impacts to individuals, groups, communities, organizations and society are characterized/understood. | C16: Assess likelihood and magnitude of impacts, incl. via consultation with affected communities where relevant. | G16: None - governance/process-level outcome. | H16: Impact assessment documentation | I16: Yes | J16: Not started
A17: MEASURE | B17: MEASURE - testing, evaluation and monitoring (system-level)
A18: Measure 1 | B18: Appropriate methods and metrics are identified and applied to AI risks, and effectiveness of metrics evaluated. | C18: Select and document metrics for measuring AI risks (performance, fairness, robustness, etc.). | G18: None - governance/process-level outcome. | H18: Metrics catalogue, methodology documentation | I18: Yes | J18: Not started
A19: Measure 2 | B19: AI systems are evaluated for trustworthy characteristics: valid/reliable, safe, secure/resilient, accountable/transparent, explainable/interpretable, privacy-enhanced, fair with harmful bias managed. | C19: Test and document evaluation of each trustworthy characteristic, incl. security and resilience testing against adversarial/abuse scenarios. | D19: ● | E19: ● | F19: ● | G19: 'Secure and resilient' is an explicit trustworthy characteristic requiring testing against attacks, unauthorized access and manipulation - directly CIA. | H19: Test reports covering security/resilience, robustness, bias, privacy | I19: Yes | J19: Not started
A20: Measure 3 | B20: Mechanisms for tracking identified AI risks over time are in place. | C20: Implement ongoing monitoring/tracking of identified risks (incl. security incidents, drift, anomalies) with regular review. | E20: ● | F20: ● | G20: Continuous monitoring must detect security-relevant drift, anomalies and incidents to preserve integrity and availability. | H20: Risk tracking log, monitoring dashboards, incident tracking | I20: Yes | J20: Not started
A21: Measure 4 | B21: Feedback about efficacy of measurement is gathered and assessed. | C21: Gather feedback (incl. from red-teaming, external audits, user reports) and use it to improve measurement approaches. | G21: None - governance/process-level outcome. | H21: Feedback records, red-team/audit reports | I21: Yes | J21: Not started
A22: MANAGE | B22: MANAGE - risk prioritization, treatment and response (system-level)
A23: Manage 1 | B23: AI risks based on assessments from the Map and Measure functions are prioritized, responded to and managed. | C23: Prioritize and treat AI risks per organizational risk tolerance; document risk response decisions. | G23: None - governance/process-level outcome. | H23: Risk treatment plan, prioritization criteria | I23: Yes | J23: Not started
A24: Manage 2 | B24: Strategies to maximize AI benefits and minimize negative impacts are planned, prepared, implemented, documented and informed by input from relevant AI actors. | C24: Implement mitigation strategies and periodically reassess effectiveness. | G24: None - governance/process-level outcome. | H24: Mitigation plan, effectiveness reviews | I24: Yes | J24: Not started
A25: Manage 3 | B25: AI risks and benefits from third-party entities are managed. | C25: Monitor and manage risks from third-party AI systems/components throughout their lifecycle, incl. contractual and technical controls. | D25: ● | G25: Managing security risk from third-party AI systems/components on an ongoing basis (patches, vulnerabilities, access). | H25: Third-party risk register, ongoing supplier monitoring | I25: Yes | J25: Not started
A26: Manage 4 | B26: Risk treatments, incl. response and recovery, and communication plans for the identified and measured AI risks are documented and monitored regularly. | C26: Establish and test incident response/recovery plans for AI-related incidents; maintain communication plans for affected stakeholders and authorities. | D26: ● | E26: ● | F26: ● | G26: Incident response and recovery for AI systems directly protects confidentiality, integrity and availability when things go wrong. | H26: AI incident response/recovery plan, communication plan, test/exercise records | I26: Yes | J26: Not started

Sheet 6 ISO 42005 Impact Assessment
A1: ISO/IEC 42005:2025 - AI System Impact Assessment (AISIA) Checklist, with CIA-Security Marking
A3: Ref | B3: Title | C3: Guidance point | D3: C | E3: I | F3: A | G3: Security note / why CIA is involved | H3: Evidence to verify | I3: Applicable | J3: Status | K3: Owner | L3: Notes / Gap
A4: Clause 4 | B4: General / terms and definitions
A5: 4 | B5: Terms, definitions and overview of AI system impact assessment (AISIA) | C5: Adopt the standard's terminology (AI system impact assessment, affected stakeholder, AI actor, etc.) and understand its purpose: assessing how an AI system and its foreseeable applications may affect individuals, groups and society across the lifecycle. | G5: None - ethical/societal/governance guidance point. | H5: Glossary/definitions reference | I5: Yes | J5: Not started
A6: Clause 5 | B6: Developing and implementing an AI system impact assessment (AISIA) process
A7: 5.1 | B7: Purpose and scope of the AISIA process | C7: Establish why and for which AI systems/use cases the organization will perform impact assessments, and how the process applies across sizes/types of organization. | G7: None - ethical/societal/governance guidance point. | H7: AISIA process charter/scope statement | I7: Yes | J7: Not started
A8: 5.2 | B8: Roles and responsibilities | C8: Assign roles for conducting, reviewing and approving impact assessments (e.g. assessors, AI system owner, independent reviewer, affected-party liaison). | G8: None - ethical/societal/governance guidance point. | H8: RACI for AISIA, appointment records | I8: Yes | J8: Not started
A9: 5.3 | B9: Triggers and timing across the AI system lifecycle | C9: Determine when an AISIA is performed or updated: initial design, before deployment, on significant change, periodically in operation, and at decommissioning. | G9: None - ethical/societal/governance guidance point. | H9: AISIA trigger criteria, lifecycle checkpoint schedule | I9: Yes | J9: Not started
A10: 5.4 | B10: Planning the assessment | C10: Plan scope, resources, timeline, methodology and tools for each AISIA, proportionate to the AI system's risk and context. | G10: None - ethical/societal/governance guidance point. | H10: AISIA plan per system | I10: Yes | J10: Not started
A11: 5.5 | B11: Understanding context and intended/foreseeable use | C11: Gather information on the AI system's purpose, intended use, reasonably foreseeable misuse, deployment context and data used. | G11: None - ethical/societal/governance guidance point. | H11: Context/use documentation, misuse scenarios | I11: Yes | J11: Not started
A12: 5.6 | B12: Identifying affected stakeholders | C12: Identify individuals, groups, communities and society that could be affected by the AI system, directly or indirectly. | G12: None - ethical/societal/governance guidance point. | H12: Affected-stakeholder inventory | I12: Yes | J12: Not started
A13: 5.7 | B13: Identifying potential impacts | C13: Identify potential positive and negative impacts (e.g. on rights, safety, fairness, autonomy, economic, environmental, security-related harms) arising from intended and foreseeable use. | D13: ● | G13: Identification should include impacts from security failures (e.g. unauthorized disclosure or manipulation of personal data) alongside ethical/societal harms. | H13: Impact identification workshop outputs/checklist | I13: Yes | J13: Not started
A14: 5.8 | B14: Analysing and evaluating impacts | C14: Analyse likelihood and severity of identified impacts, and evaluate them against organizational risk criteria and stakeholder expectations. | G14: None - ethical/societal/governance guidance point. | H14: Impact analysis/evaluation records | I14: Yes | J14: Not started
A15: 5.9 | B15: Determining and implementing mitigation actions | C15: Identify options to prevent, reduce or otherwise address negative impacts, decide and implement appropriate actions, and record residual impact. | G15: None - ethical/societal/governance guidance point. | H15: Mitigation action plan, residual impact sign-off | I15: Yes | J15: Not started
A16: 5.10 | B16: Review, monitoring and reassessment | C16: Monitor the AI system and its context for change, and review/update the impact assessment periodically or when triggers in 5.3 occur. | G16: None - ethical/societal/governance guidance point. | H16: Review schedule, reassessment records | I16: Yes | J16: Not started
A17: 5.11 | B17: Integration with AI risk management and the AI management system | C17: Integrate AISIA outputs into the organization's AI risk assessment/treatment process and AI management system (e.g. ISO/IEC 42001 clauses 6.1.2 and 6.1.4). | G17: None - ethical/societal/governance guidance point. | H17: AIMS/risk-register cross-references | I17: Yes | J17: Not started
A18: Clause 6 | B18: Documenting the AI system impact assessment
A19: 6.1 | B19: General documentation requirements | C19: Determine what information must be documented for each AISIA to support transparency, accountability and traceability of the process and its outcomes. | G19: None - ethical/societal/governance guidance point. | H19: Documentation standard/template | I19: Yes | J19: Not started
A20: 6.2 | B20: Content of the impact assessment record | C20: Document scope, context, affected stakeholders, identified impacts, analysis/evaluation, decisions, mitigation actions and residual impacts, and who approved the assessment. | G20: None - ethical/societal/governance guidance point. | H20: Completed AISIA report(s) | I20: Yes | J20: Not started
A21: 6.3 | B21: Retention, version control and integrity of records | C21: Maintain AISIA documentation over time, with version control, so records remain accurate, traceable and available for the required retention period. | E21: ● | G21: Impact-assessment records must retain integrity and be protected from unauthorized alteration to remain a trustworthy audit trail. | H21: Document retention policy, version history | I21: Yes | J21: Not started
A22: 6.4 | B22: Communication of results | C22: Determine what impact assessment information is communicated to interested parties (e.g. management, regulators, affected stakeholders) and how. | G22: None - ethical/societal/governance guidance point. | H22: Communication plan/records, published summaries where applicable | I22: Yes | J22: Not started
A23: 6.5 | B23: Confidentiality and access control of assessment records | C23: Control access to AISIA documentation appropriately, since records may contain sensitive information about individuals, vulnerabilities or system design. | D23: ● | G23: Impact assessment records can reveal personal data, vulnerabilities or system weaknesses and need confidentiality protection. | H23: Access control on AISIA repository | I23: Yes | J23: Not started
A24: Annexes | B24: Informative annexes
A25: Annex A | B25: Guidance for use with ISO/IEC 42001 | C25: Use this annex to align the AISIA process with the AI management system requirements of ISO/IEC 42001, incl. clauses 6.1.2 (AI risk assessment), 6.1.4 (AI system impact assessment) and Annex A.5 controls. | G25: None - ethical/societal/governance guidance point. | H25: Cross-reference to ISO 42001 6.1.2/6.1.4/A.5 items in this workbook | I25: Yes | J25: Not started
A26: Annex B | B26: Guidance for use with ISO/IEC 23894 | C26: Use this annex to align the AISIA process with AI risk management guidance in ISO/IEC 23894 (built on ISO 31000). | G26: None - ethical/societal/governance guidance point. | H26: Cross-reference to AI risk management process | I26: Yes | J26: Not started
A27: Annex C-D | B27: Example impact categories and considerations | C27: Consider the standard's example impact categories (e.g. individual, group, societal, environmental) and illustrative considerations when identifying impacts in 5.7. | G27: None - ethical/societal/governance guidance point. | H27: Impact category checklist used in assessments | I27: Yes | J27: Not started
A28: Annex E | B28: AI system impact assessment template | C28: Use or adapt the standard's AISIA template to structure and document individual assessments consistently across the organization. | G28: None - ethical/societal/governance guidance point. | H28: Organization's adapted AISIA template | I28: Yes | J28: Not started

Sheet 7 ISO 27001
A1: ISO/IEC 27001:2022 - Clause & Annex A Checklist, with CIA Marking
A3: Ref | B3: Title | C3: Security requirement | D3: C | E3: I | F3: A | G3: Why CIA is involved | H3: Evidence to verify | I3: Applicable | J3: Status | K3: Owner | L3: Notes / Gap
A4: Clauses 4-10 (mandatory ISMS requirements)
A5: 4 | B5: Context of the organization
A6: 4.1 | B6: Understanding the organization and its context | C6: Determine external/internal issues relevant to ISMS purpose and intended outcomes. | G6: None - governance/process requirement without a direct CIA-protection function. | H6: Context analysis (PESTLE/SWOT), issue register | I6: Yes | J6: Not started
A7: 4.2 | B7: Understanding needs and expectations of interested parties | C7: Identify interested parties, their ISMS-relevant requirements (legal, regulatory, contractual) and which are addressed by the ISMS. | G7: None - governance/process requirement without a direct CIA-protection function. | H7: Interested-parties register, legal/regulatory register (e.g. PDPPL, QCB/CRA) | I7: Yes | J7: Not started
A8: 4.3 | B8: Determining the scope of the ISMS | C8: Define and document ISMS boundaries and applicability, considering 4.1, 4.2 and interfaces/dependencies. | G8: None - governance/process requirement without a direct CIA-protection function. | H8: Approved scope statement | I8: Yes | J8: Not started
A9: 4.4 | B9: Information security management system | C9: Establish, implement, maintain and continually improve the ISMS, including needed processes and interactions. | G9: None - governance/process requirement without a direct CIA-protection function. | H9: ISMS manual/process map | I9: Yes | J9: Not started
A10: 5 | B10: Leadership
A11: 5.1 | B11: Leadership and commitment | C11: Top management demonstrates commitment: policy/objectives aligned to strategy, ISMS integrated in processes, resources provided, importance communicated, outcomes ensured, improvement promoted. | G11: None - governance/process requirement without a direct CIA-protection function. | H11: Management minutes, budget approvals, sponsor communications | I11: Yes | J11: Not started
A12: 5.2 | B12: Policy | C12: Establish an information security policy suited to the purpose, providing objectives/framework, commitment to requirements and continual improvement; documented, communicated, available to interested parties. | G12: None - governance/process requirement without a direct CIA-protection function. | H12: Signed policy, distribution/acknowledgement records | I12: Yes | J12: Not started
A13: 5.3 | B13: Organizational roles, responsibilities and authorities | C13: Assign and communicate ISMS roles, incl. responsibility for conformity and for reporting performance to top management. | G13: None - governance/process requirement without a direct CIA-protection function. | H13: RACI, role descriptions, appointment letters | I13: Yes | J13: Not started
A14: 6 | B14: Planning
A15: 6.1.1 | B15: Actions to address risks and opportunities - General | C15: Plan actions for risks/opportunities from 4.1 and 4.2 so ISMS achieves outcomes, prevents undesired effects and improves; integrate and evaluate effectiveness. | G15: None - governance/process requirement without a direct CIA-protection function. | H15: Risk & opportunity register | I15: Yes | J15: Not started
A16: 6.1.2 | B16: Information security risk assessment | C16: Define and apply a risk assessment process: risk criteria, repeatable/comparable results, identify risks and owners, analyse likelihood/consequence, evaluate against criteria; retain documented information. | D16: ● | E16: ● | F16: ● | G16: Security risk assessment process covering confidentiality, integrity and availability risks. | H16: Risk methodology, risk register, risk assessment reports | I16: Yes | J16: Not started
A17: 6.1.3 | B17: Information security risk treatment | C17: Select treatment options; determine all necessary controls (compare against Annex A); produce Statement of Applicability with justification for inclusions/exclusions; formulate treatment plan; obtain risk owner approval of plan and residual risk. | D17: ● | E17: ● | F17: ● | G17: Selects and treats security risks/controls across CIA. | H17: Risk treatment plan, SoA, residual risk acceptance | I17: Yes | J17: Not started
A18: 6.2 | B18: Information security objectives and planning to achieve them | C18: Set measurable, monitored, communicated objectives consistent with policy; plan what, resources, owner, deadline, evaluation. | G18: None - governance/process requirement without a direct CIA-protection function. | H18: Objectives register, KPI/KRI plan | I18: Yes | J18: Not started
A19: 6.3 | B19: Planning of changes | C19: Carry out ISMS changes (identified as needed) in a planned manner. | G19: None - governance/process requirement without a direct CIA-protection function. | H19: Change records for ISMS, impact assessments | I19: Yes | J19: Not started
A20: 7 | B20: Support
A21: 7.1 | B21: Resources | C21: Determine and provide resources needed for establishing, implementing, maintaining and improving the ISMS. | G21: None - governance/process requirement without a direct CIA-protection function. | H21: Budget, staffing plan | I21: Yes | J21: Not started
A22: 7.2 | B22: Competence | C22: Determine necessary competence of persons affecting security performance; ensure competence via education/training/experience; take actions and retain evidence. | G22: None - governance/process requirement without a direct CIA-protection function. | H22: Skills matrix, training/certification records | I22: Yes | J22: Not started
A23: 7.3 | B23: Awareness | C23: Ensure persons are aware of policy, their contribution to ISMS effectiveness and implications of non-conformity. | G23: None - governance/process requirement without a direct CIA-protection function. | H23: Awareness programme, attendance/phishing-test records | I23: Yes | J23: Not started
A24: 7.4 | B24: Communication | C24: Determine internal/external ISMS communications: what, when, with whom, who communicates, and process. | G24: None - governance/process requirement without a direct CIA-protection function. | H24: Communication plan | I24: Yes | J24: Not started
A25: 7.5.1 | B25: Documented information - General | C25: ISMS includes documented information required by the standard and determined necessary for effectiveness. | G25: None - governance/process requirement without a direct CIA-protection function. | H25: Document register | I25: Yes | J25: Not started
A26: 7.5.2 | B26: Creating and updating | C26: Ensure appropriate identification/description, format/media, review and approval. | G26: None - governance/process requirement without a direct CIA-protection function. | H26: Document templates, approval workflow | I26: Yes | J26: Not started
A27: 7.5.3 | B27: Control of documented information | C27: Control availability, protection, distribution, access, storage, version control, retention/disposition; control external-origin documents. | D27: ● | E27: ● | G27: Protecting documented information from unauthorized access and alteration. | H27: DMS configuration, access and retention rules | I27: Yes | J27: Not started
A28: 8 | B28: Operation
A29: 8.1 | B29: Operational planning and control | C29: Plan, implement and control processes to meet requirements and 6.1 actions; set criteria; keep documented information; control planned changes and outsourced processes. | G29: None - governance/process requirement without a direct CIA-protection function. | H29: Operating procedures, outsourcing controls | I29: Yes | J29: Not started
A30: 8.2 | B30: Information security risk assessment | C30: Perform risk assessments at planned intervals or on significant change; retain results. | D30: ● | E30: ● | F30: ● | G30: Operational security risk assessment. | H30: Dated risk assessment outputs | I30: Yes | J30: Not started
A31: 8.3 | B31: Information security risk treatment | C31: Implement the risk treatment plan; retain results of treatment. | D31: ● | E31: ● | F31: ● | G31: Operational implementation of security risk treatment. | H31: Treatment plan status, closure evidence | I31: Yes | J31: Not started
A32: 9 | B32: Performance evaluation
A33: 9.1 | B33: Monitoring, measurement, analysis and evaluation | C33: Determine what to monitor/measure, methods, when, who; evaluate security performance and ISMS effectiveness; retain evidence. | G33: None - governance/process requirement without a direct CIA-protection function. | H33: Metrics dashboards, KPI reports | I33: Yes | J33: Not started
A34: 9.2.1 | B34: Internal audit - General | C34: Conduct internal audits at planned intervals to check conformity to own requirements and the standard, and effective implementation. | G34: None - governance/process requirement without a direct CIA-protection function. | H34: Audit programme, audit reports | I34: Yes | J34: Not started
A35: 9.2.2 | B35: Internal audit programme | C35: Plan programme (frequency, methods, responsibilities, reporting); define criteria/scope; select objective, impartial auditors; report to management; retain evidence. | G35: None - governance/process requirement without a direct CIA-protection function. | H35: Audit plan, auditor independence records, findings log | I35: Yes | J35: Not started
A36: 9.3.1 | B36: Management review - General | C36: Top management reviews the ISMS at planned intervals for suitability, adequacy, effectiveness. | G36: None - governance/process requirement without a direct CIA-protection function. | H36: Management review schedule and minutes | I36: Yes | J36: Not started
A37: 9.3.2 | B37: Management review inputs | C37: Consider status of previous actions, changes in issues, feedback on performance (NCs, monitoring, audits, objectives), interested-party feedback, risk assessment/treatment status, improvement opportunities. | G37: None - governance/process requirement without a direct CIA-protection function. | H37: Management review pack | I37: Yes | J37: Not started
A38: 9.3.3 | B38: Management review results | C38: Record decisions on improvement opportunities and any ISMS changes; retain as documented information. | G38: None - governance/process requirement without a direct CIA-protection function. | H38: Minutes, action tracker | I38: Yes | J38: Not started
A39: 10 | B39: Improvement
A40: 10.1 | B40: Continual improvement | C40: Continually improve the suitability, adequacy and effectiveness of the ISMS. | G40: None - governance/process requirement without a direct CIA-protection function. | H40: Improvement register, trend analysis | I40: Yes | J40: Not started
A41: 10.2 | B41: Nonconformity and corrective action | C41: React to NCs, evaluate need to eliminate causes, implement and review corrective action for effectiveness, update ISMS; retain evidence. | G41: None - governance/process requirement without a direct CIA-protection function. | H41: NC/CAPA log, root-cause analyses | I41: Yes | J41: Not started
A42: Annex A controls (93)
A43: A.5 | B43: Organizational controls
A44: 5.1 | B44: Policies for information security | C44: Define, approve, publish, communicate and review the information security policy and topic-specific policies at planned intervals. | G44: None - governance/process requirement without a direct CIA-protection function. | H44: Policy set, review history | I44: Yes | J44: Not started
A45: 5.2 | B45: Information security roles and responsibilities | C45: Define and allocate security roles per organizational needs. | G45: None - governance/process requirement without a direct CIA-protection function. | H45: RACI, job descriptions | I45: Yes | J45: Not started
A46: 5.3 | B46: Segregation of duties | C46: Segregate conflicting duties and areas of responsibility. | E46: ● | G46: Segregation of duties reduces risk of undetected fraud/error affecting integrity. | H46: SoD matrix, access reviews | I46: Yes | J46: Not started
A47: 5.4 | B47: Management responsibilities | C47: Management requires all personnel to apply security per policies and procedures. | G47: None - governance/process requirement without a direct CIA-protection function. | H47: Management directives, acknowledgements | I47: Yes | J47: Not started
A48: 5.5 | B48: Contact with authorities | C48: Maintain contact with relevant authorities (e.g. regulator, CERT, law enforcement). | G48: None - governance/process requirement without a direct CIA-protection function. | H48: Contact list, notification procedure | I48: Yes | J48: Not started
A49: 5.6 | B49: Contact with special interest groups | C49: Maintain contact with security forums and professional associations. | G49: None - governance/process requirement without a direct CIA-protection function. | H49: Memberships, advisory feeds | I49: Yes | J49: Not started
A50: 5.7 | B50: Threat intelligence | C50: Collect and analyse information on threats to produce threat intelligence. | D50: ● | E50: ● | F50: ● | G50: Threat intelligence informs defenses across confidentiality, integrity and availability. | H50: TI sources, TI reports, use in risk/detection | I50: Yes | J50: Not started
A51: 5.8 | B51: Information security in project management | C51: Integrate security into project management across all projects. | G51: None - governance/process requirement without a direct CIA-protection function. | H51: Project security checklists, security gates | I51: Yes | J51: Not started
A52: 5.9 | B52: Inventory of information and other associated assets | C52: Develop and maintain inventory of information and associated assets with owners. | E52: ● | G52: Asset inventory is foundational to knowing what needs protecting. | H52: Asset register/CMDB | I52: Yes | J52: Not started
A53: 5.10 | B53: Acceptable use of information and other associated assets | C53: Identify, document and implement rules for acceptable use and handling. | D53: ● | G53: Acceptable use limits misuse that could expose information. | H53: AUP, user acknowledgement | I53: Yes | J53: Not started
A54: 5.11 | B54: Return of assets | C54: Personnel and other parties return all assets on change or termination. | D54: ● | G54: Ensures assets/data are not retained inappropriately after use. | H54: Offboarding checklist | I54: Yes | J54: Not started
A55: 5.12 | B55: Classification of information | C55: Classify information by confidentiality, integrity, availability and interested-party requirements. | D55: ● | G55: Classification underpins confidentiality protection. | H55: Classification scheme, classified inventory | I55: Yes | J55: Not started
A56: 5.13 | B56: Labelling of information | C56: Develop and implement labelling procedures per classification scheme. | D56: ● | G56: Labelling supports correct handling per confidentiality level. | H56: Labelling procedure, DLP/label config | I56: Yes | J56: Not started
A57: 5.14 | B57: Information transfer | C57: Establish transfer rules, procedures or agreements for all transfer facilities. | D57: ● | E57: ● | F57: ● | G57: Transfer controls protect data in transit. | H57: Transfer policy, NDAs/agreements, secure transfer tools | I57: Yes | J57: Not started
A58: 5.15 | B58: Access control | C58: Establish and implement rules to control physical and logical access based on business and security requirements. | D58: ● | E58: ● | F58: ● | G58: Core access control protecting all three properties. | H58: Access control policy | I58: Yes | J58: Not started
A59: 5.16 | B59: Identity management | C59: Manage the full life cycle of identities. | D59: ● | E59: ● | F59: ● | G59: Identity lifecycle management underpins access security. | H59: Joiner/mover/leaver process, IAM records | I59: Yes | J59: Not started
A60: 5.17 | B60: Authentication information | C60: Control allocation and management of authentication information incl. user guidance. | D60: ● | E60: ● | F60: ● | G60: Authentication information protects access to systems. | H60: Password/MFA standard, credential issuance process | I60: Yes | J60: Not started
A61: 5.18 | B61: Access rights | C61: Provision, review, modify and remove access rights per policy. | D61: ● | E61: ● | F61: ● | G61: Access rights management controls who can reach what. | H61: Access requests, periodic recertification | I61: Yes | J61: Not started
A62: 5.19 | B62: Information security in supplier relationships | C62: Define and implement processes to manage supplier-related security risks. | D62: ● | E62: ● | F62: ● | G62: Supplier risk affects confidentiality, integrity and availability of shared assets. | H62: Supplier security policy, risk assessments | I62: Yes | J62: Not started
A63: 5.20 | B63: Addressing information security within supplier agreements | C63: Establish and agree relevant security requirements with each supplier. | D63: ● | E63: ● | F63: ● | G63: Contractual security requirements with suppliers. | H63: Contract security clauses, DPAs | I63: Yes | J63: Not started
A64: 5.21 | B64: Managing information security in the ICT supply chain | C64: Manage security risks in ICT products/services supply chain. | D64: ● | E64: ● | F64: ● | G64: ICT supply chain risk (compromised components/software). | H64: Supply chain requirements, SBOM/attestations | I64: Yes | J64: Not started
A65: 5.22 | B65: Monitoring, review and change management of supplier services | C65: Regularly monitor, review, evaluate and manage change in supplier practices and service delivery. | D65: ● | E65: ● | F65: ● | G65: Ongoing supplier monitoring for security posture. | H65: Supplier reviews, SLA/security reports, audit rights | I65: Yes | J65: Not started
A66: 5.23 | B66: Information security for use of cloud services | C66: Establish processes for acquisition, use, management and exit of cloud services. | D66: ● | E66: ● | F66: ● | G66: Cloud security spans all three properties. | H66: Cloud policy, shared-responsibility matrix, exit plan | I66: Yes | J66: Not started
A67: 5.24 | B67: Information security incident management planning and preparation | C67: Plan and prepare incident management: processes, roles, responsibilities. | D67: ● | E67: ● | F67: ● | G67: Incident planning underpins ability to protect CIA when incidents occur. | H67: IR policy/plan, roles, playbooks | I67: Yes | J67: Not started
A68: 5.25 | B68: Assessment and decision on information security events | C68: Assess events and decide whether to classify as incidents. | D68: ● | E68: ● | F68: ● | G68: Assessing events to determine CIA impact. | H68: Triage criteria, event logs | I68: Yes | J68: Not started
A69: 5.26 | B69: Response to information security incidents | C69: Respond to incidents per documented procedures. | D69: ● | E69: ● | F69: ● | G69: Responding to incidents restores CIA. | H69: Incident records, response evidence | I69: Yes | J69: Not started
A70: 5.27 | B70: Learning from information security incidents | C70: Use knowledge from incidents to strengthen controls. | E70: ● | G70: Lessons learned improve control integrity/effectiveness. | H70: Post-incident reviews, lessons learned | I70: Yes | J70: Not started
A71: 5.28 | B71: Collection of evidence | C71: Establish procedures for identification, collection, acquisition and preservation of evidence. | E71: ● | G71: Evidence collection preserves integrity for investigations. | H71: Forensic procedure, chain-of-custody forms | I71: Yes | J71: Not started
A72: 5.29 | B72: Information security during disruption | C72: Plan how to maintain security at an appropriate level during disruption. | F72: ● | G72: Maintaining security during disruption protects availability. | H72: BCP security provisions | I72: Yes | J72: Not started
A73: 5.30 | B73: ICT readiness for business continuity | C73: Plan, implement, maintain and test ICT readiness based on BC objectives and ICT continuity requirements. | F73: ● | G73: ICT continuity protects availability. | H73: BIA, DR plans, DR test results (RTO/RPO) | I73: Yes | J73: Not started
A74: 5.31 | B74: Legal, statutory, regulatory and contractual requirements | C74: Identify, document and keep current legal/regulatory/contractual requirements and how they are met. | G74: None - governance/process requirement without a direct CIA-protection function. | H74: Legal register, compliance mapping | I74: Yes | J74: Not started
A75: 5.32 | B75: Intellectual property rights | C75: Implement procedures to protect intellectual property rights. | D75: ● | G75: Protects confidentiality of licensed/IP material. | H75: Licence inventory, IP policy | I75: Yes | J75: Not started
A76: 5.33 | B76: Protection of records | C76: Protect records from loss, destruction, falsification, unauthorized access and release. | D76: ● | E76: ● | G76: Protects records from loss, falsification or unauthorized release. | H76: Records retention schedule, protection controls | I76: Yes | J76: Not started
A77: 5.34 | B77: Privacy and protection of PII | C77: Identify and meet requirements for privacy and PII protection per law and contract. | D77: ● | G77: Protects confidentiality of personal data. | H77: Privacy policy, ROPA, DPIAs, DSAR process | I77: Yes | J77: Not started
A78: 5.35 | B78: Independent review of information security | C78: Review the organization's security approach independently at planned intervals and on significant change. | G78: None - governance/process requirement without a direct CIA-protection function. | H78: Independent review/audit reports | I78: Yes | J78: Not started
A79: 5.36 | B79: Compliance with policies, rules and standards for information security | C79: Regularly review compliance with policies, topic-specific policies, rules and standards. | G79: None - governance/process requirement without a direct CIA-protection function. | H79: Compliance checks, technical compliance reports | I79: Yes | J79: Not started
A80: 5.37 | B80: Documented operating procedures | C80: Document operating procedures and make available to personnel who need them. | E80: ● | G80: Documented procedures support consistent, correct (integrity) operations. | H80: Runbooks, SOPs | I80: Yes | J80: Not started
A81: A.6 | B81: People controls
A82: 6.1 | B82: Screening | C82: Verify candidates' background before joining and on an ongoing basis per laws and risk. | G82: None - governance/process requirement without a direct CIA-protection function. | H82: Screening records | I82: Yes | J82: Not started
A83: 6.2 | B83: Terms and conditions of employment | C83: Employment agreements state personnel and organizational security responsibilities. | G83: None - governance/process requirement without a direct CIA-protection function. | H83: Signed contracts | I83: Yes | J83: Not started
A84: 6.3 | B84: Information security awareness, education and training | C84: Provide appropriate awareness, education, training and regular policy updates. | G84: None - governance/process requirement without a direct CIA-protection function. | H84: Training plan, completion metrics | I84: Yes | J84: Not started
A85: 6.4 | B85: Disciplinary process | C85: Formalize and communicate a disciplinary process for security policy violations. | G85: None - governance/process requirement without a direct CIA-protection function. | H85: Disciplinary policy | I85: Yes | J85: Not started
A86: 6.5 | B86: Responsibilities after termination or change of employment | C86: Define, enforce and communicate security duties that remain valid after termination/change. | D86: ● | G86: Post-employment confidentiality obligations continue. | H86: Exit procedures, reminders of obligations | I86: Yes | J86: Not started
A87: 6.6 | B87: Confidentiality or non-disclosure agreements | C87: Identify, document, review and sign NDAs reflecting protection needs. | D87: ● | G87: NDAs protect confidentiality of shared information. | H87: Signed NDAs, template review | I87: Yes | J87: Not started
A88: 6.7 | B88: Remote working | C88: Implement security measures when personnel work remotely. | D88: ● | E88: ● | F88: ● | G88: Remote working introduces risk across all three properties. | H88: Remote working policy, VPN/MDM controls | I88: Yes | J88: Not started
A89: 6.8 | B89: Information security event reporting | C89: Provide a mechanism for personnel to report observed/suspected events promptly. | E89: ● | G89: Timely event reporting preserves integrity of response. | H89: Reporting channel, awareness of channel | I89: Yes | J89: Not started
A90: A.7 | B90: Physical controls
A91: 7.1 | B91: Physical security perimeters | C91: Define and use security perimeters to protect areas with information and assets. | D91: ● | F91: ● | G91: Perimeters protect against unauthorized physical access and disruption. | H91: Site plans, perimeter controls | I91: Yes | J91: Not started
A92: 7.2 | B92: Physical entry | C92: Protect secure areas with entry controls and access points. | D92: ● | F92: ● | G92: Entry controls limit unauthorized physical access. | H92: Badge logs, visitor management | I92: Yes | J92: Not started
A93: 7.3 | B93: Securing offices, rooms and facilities | C93: Design and implement physical security for offices, rooms and facilities. | D93: ● | F93: ● | G93: Facility security protects assets housed within. | H93: Facility security assessment | I93: Yes | J93: Not started
A94: 7.4 | B94: Physical security monitoring | C94: Continuously monitor premises for unauthorized physical access. | D94: ● | G94: Monitoring detects unauthorized physical access. | H94: CCTV, intrusion alarms, retention config | I94: Yes | J94: Not started
A95: 7.5 | B95: Protecting against physical and environmental threats | C95: Design and implement protection against fire, flood, and other natural or man-made threats. | F95: ● | G95: Protects against environmental threats to availability. | H95: Fire suppression, environmental sensors, inspections | I95: Yes | J95: Not started
A96: 7.6 | B96: Working in secure areas | C96: Design and implement security measures for working in secure areas. | D96: ● | G96: Secure-area working rules protect confidentiality. | H96: Secure area procedures | I96: Yes | J96: Not started
A97: 7.7 | B97: Clear desk and clear screen | C97: Define and enforce clear desk (papers/media) and clear screen rules. | D97: ● | G97: Clear desk/screen reduces exposure of sensitive information. | H97: Policy, screen-lock config, spot checks | I97: Yes | J97: Not started
A98: 7.8 | B98: Equipment siting and protection | C98: Site and protect equipment to reduce environmental risks and unauthorized access. | D98: ● | F98: ● | G98: Equipment siting reduces environmental and access risk. | H98: Data centre/rack layout, inspections | I98: Yes | J98: Not started
A99: 7.9 | B99: Security of assets off-premises | C99: Protect off-site assets. | D99: ● | F99: ● | G99: Protects assets used outside the office. | H99: Off-site asset rules, encryption | I99: Yes | J99: Not started
A100: 7.10 | B100: Storage media | C100: Manage storage media through acquisition, use, transport and disposal per classification. | D100: ● | E100: ● | G100: Media handling protects data confidentiality and integrity. | H100: Media handling procedure, encryption, logs | I100: Yes | J100: Not started
A101: 7.11 | B101: Supporting utilities | C101: Protect facilities from power failures and other utility disruptions. | F101: ● | G101: Utilities support availability of processing facilities. | H101: UPS/generator tests, redundancy | I101: Yes | J101: Not started
...

Sheet 8 ISO 17021 Alignment
A1: ISO/IEC 17021-1:2015 - Certification-Body Requirements & Audit-Readiness Alignment (with CIA Marking)
A3: Ref | B3: Title | C3: Certification body (CB) requirement | D3: Audit-readiness alignment for the certified organization | E3: ISMS / AIMS cross-reference | F3: C | G3: I | H3: A | I3: Why CIA is involved | J3: Evidence to verify | K3: Applicable | L3: Status | M3: Owner | N3: Notes / Gap
A4: Clause 4 | B4: Principles (basis for confidence in certification)
A5: 4.1 | B5: General | C5: Certification must inspire confidence: principles of impartiality, competence, responsibility, openness, confidentiality, responsiveness to complaints and risk-based approach underpin all certification activity. | D5: Expect the audit to be conducted objectively and evidence-based; be ready to demonstrate rather than assert conformity. | E5: ISO 27001 / 42001 clause 9.2 | I5: None - process/governance requirement without a direct CIA-protection function. | J5: Audit-readiness pack, evidence index | K5: Yes | L5: Not started
A6: 4.2 | B6: Impartiality | C6: The CB must be impartial and be seen to be; decisions are based on objective evidence, free from conflicts of interest. | D6: Do not offer inducements or influence auditors; separate any consultancy from the certification audit; declare prior consulting relationships. | E6: ISO 27001 / 42001 5.1, 9.2 (independent internal audit) | I6: None - process/governance requirement without a direct CIA-protection function. | J6: Conflict-of-interest declarations, consultant/auditor separation record | K6: Yes | L6: Not started
A7: 4.3 | B7: Competence | C7: Certification personnel must have the knowledge and skills to perform certification activities for the relevant scope/sector. | D7: Confirm the CB's audit team is competent for your sector, technology (e.g. AI, cloud, telecom) and risk profile before the audit. | E7: ISO 27001 7.2 / ISO 42001 7.2 | I7: None - process/governance requirement without a direct CIA-protection function. | J7: CB team competence evidence, sector/technical-expert confirmation | K7: Yes | L7: Not started
A8: 4.4 | B8: Responsibility | C8: The client organization, not the CB, is responsible for conformity with certification requirements. | D8: Own and maintain the management system continuously; certification is not a substitute for ongoing conformity. | E8: ISO 27001 / 42001 5.1, 5.3 | I8: None - process/governance requirement without a direct CIA-protection function. | J8: Top-management commitment records, ISMS/AIMS ownership | K8: Yes | L8: Not started
A9: 4.5 | B9: Openness | C9: The CB provides appropriate public access to information about its audit process and certification status. | D9: Be aware certification status and scope can be publicly verified; ensure scope wording is accurate. | E9: ISO 27001 / 42001 4.3 (scope) | I9: None - process/governance requirement without a direct CIA-protection function. | J9: Approved scope statement | K9: Yes | L9: Not started
A10: 4.6 | B10: Confidentiality | C10: The CB must protect confidential client information obtained during certification activities. | D10: Confirm confidentiality terms in the certification agreement; control what evidence (logs, architecture, risk registers, model/data details) is shared with auditors and how. | E10: ISO 27001 A.5.14, A.5.34, A.6.6; ISO 42001 A.10.2 | F10: ● | I10: Auditors access sensitive security and AI system information; confidentiality obligations and controlled evidence sharing protect it. | J10: Certification agreement confidentiality clause, evidence-sharing controls | K10: Yes | L10: Not started
A11: 4.7 | B11: Responsiveness to complaints | C11: The CB responds effectively to complaints and appeals, with fair handling. | D11: Know the CB's complaints/appeals route in case of audit disagreement or contested findings. | E11: ISO 27001 / 42001 10.2 | I11: None - process/governance requirement without a direct CIA-protection function. | J11: CB complaints/appeals procedure reference | K11: Yes | L11: Not started
A12: 4.8 | B12: Risk-based approach | C12: The CB considers risks to impartiality, competence and consistency when planning and decision-making. | D12: Expect audit time and focus to reflect your risk profile; keep risk assessments current and evidence-ready. | E12: ISO 27001 / 42001 6.1.2, 8.2 | I12: None - process/governance requirement without a direct CIA-protection function. | J12: Current risk assessments, treatment plans | K12: Yes | L12: Not started
A13: Clause 5 | B13: General requirements
A14: 5.1 | B14: Legal and contractual matters | C14: The CB is a legal entity and has a legally enforceable certification agreement with each client, defining rights/obligations and responsibility for decisions. | D14: Review and sign the certification agreement; understand obligations (access, notification of changes, mark usage, surveillance cycle). | E14: ISO 27001 / 42001 4.2 (legal/contractual requirements) | I14: None - process/governance requirement without a direct CIA-protection function. | J14: Signed certification agreement | K14: Yes | L14: Not started
A15: 5.2 | B15: Management of impartiality | C15: The CB identifies, analyses and documents risks to impartiality and has top management commitment to it. | D15: Ensure no undisclosed consultancy or related-party relationship with the CB or audit team. | E15: ISO 27001 / 42001 5.1 | I15: None - process/governance requirement without a direct CIA-protection function. | J15: Independence declaration | K15: Yes | L15: Not started
A16: 5.3 | B16: Liability and financing | C16: The CB has arrangements (insurance/reserves) to cover liabilities from operations. | D16: Not a client obligation; confirm CB is accredited and in good standing before engaging. | E16: - | I16: None - process/governance requirement without a direct CIA-protection function. | J16: CB accreditation certificate/scope verified | K16: Yes | L16: Not started
A17: Clause 6 | B17: Structural requirements
A18: 6.1 | B18: Organizational structure and top management | C18: The CB documents its organizational structure, duties and authorities; a body/committee safeguards impartiality. | D18: Verify CB accreditation scope covers your standard (e.g. ISO/IEC 27001, ISO/IEC 42001) and sector. | E18: - | I18: None - process/governance requirement without a direct CIA-protection function. | J18: Accreditation scope check | K18: Yes | L18: Not started
A19: 6.2 | B19: Operational control | C19: The CB has a process for effective control of certification activities carried out by branch offices, partnerships, agents or franchisees. | D19: Confirm the audit is carried out under the CB's controlled process even where delivered locally. | E19: - | I19: None - process/governance requirement without a direct CIA-protection function. | J19: CB delivery-office/contracting confirmation | K19: Yes | L19: Not started
A20: Clause 7 | B20: Resource requirements
A21: 7.1 | B21: Competence of personnel | C21: The CB defines competence criteria and processes for selecting/monitoring personnel for each management system type and technical area. | D21: Ask for auditor competence for information security, AI management, cloud and telecom-specific technology as applicable. | E21: ISO 27001 / 42001 7.2 | I21: None - process/governance requirement without a direct CIA-protection function. | J21: Auditor competence records requested/reviewed | K21: Yes | L21: Not started
A22: 7.2 | B22: Personnel involved in certification activities | C22: The CB has sufficient competent personnel (auditors, reviewers, decision-makers); contracts and training are in place. | D22: Be ready to accommodate the assigned audit team; raise any competence concerns before the audit. | E22: - | I22: None - process/governance requirement without a direct CIA-protection function. | J22: Audit team details | K22: Yes | L22: Not started
A23: 7.3 | B23: Use of individual external auditors and technical experts | C23: External auditors/experts operate under the CB's contract, impartiality and confidentiality requirements. | D23: Confirm external technical experts are bound by confidentiality and conflict-of-interest rules. | E23: ISO 27001 A.5.19-A.5.20 (supplier/third-party access) | I23: None - process/governance requirement without a direct CIA-protection function. | J23: External expert confidentiality confirmation | K23: Yes | L23: Not started
A24: 7.4 | B24: Personnel records | C24: The CB maintains up-to-date records of qualifications, training, experience and performance of personnel. | D24: Not a client obligation; you may request evidence of auditor qualifications. | E24: - | F24: ● | G24: ● | I24: CB personnel records contain personal data needing confidentiality and integrity. | J24: Auditor qualification evidence (on request) | K24: Yes | L24: Not started
A25: 7.5 | B25: Outsourcing | C25: The CB retains responsibility when outsourcing audit activities and has a legally binding agreement covering confidentiality and impartiality. | D25: Confirm whether any audit activity is outsourced and that outsourcing agreements protect your information. | E25: ISO 27001 A.5.19-A.5.22; ISO 42001 A.10.2-A.10.3 | F25: ● | I25: Outsourced audit parties gain access to client information; agreements must protect confidentiality. | J25: Outsourcing declaration, confidentiality agreement | K25: Yes | L25: Not started
A26: Clause 8 | B26: Information requirements
A27: 8.1 | B27: Public information | C27: The CB publicly provides information on its audit processes, certification process, and granting/suspending/withdrawing certification. | D27: Read the CB's published process so audit steps and timelines are expected. | E27: - | I27: None - process/governance requirement without a direct CIA-protection function. | J27: CB process documentation reviewed | K27: Yes | L27: Not started
A28: 8.2 | B28: Certification documents | C28: The CB gives certification documents identifying the client, standard, scope, and validity. | D28: Verify certificate scope, standard version and validity dates are accurate; report inaccuracies promptly. | E28: ISO 27001 / 42001 4.3 | G28: ● | I28: Certificates are trust artefacts; accuracy and protection from tampering/forgery preserve their integrity. | J28: Issued certificate verified against scope and SoA | K28: Yes | L28: Not started
A29: 8.3 | B29: Reference to certification and use of marks | C29: The CB controls use of certification marks; clients must not misuse certification or mislead about scope. | D29: Use marks and certification claims only within the certified scope and per CB rules. | E29: - | G29: ● | I29: Misrepresentation of certification undermines the integrity of the certification claim. | J29: Marks-usage rules and approved communications | K29: Yes | L29: Not started
A30: 8.4 | B30: Confidentiality | C30: The CB keeps information about clients confidential, has a legally enforceable commitment, and informs the client before disclosing to third parties unless required by law. | D30: Agree what information can be disclosed to regulators/accreditation bodies; require notification of any legally required disclosure. | E30: ISO 27001 A.5.34, A.6.6; ISO 42001 A.10.2 | F30: ● | I30: Direct confidentiality obligation over client security and AI system information. | J30: Confidentiality terms, disclosure-notification clause | K30: Yes | L30: Not started
A31: 8.5 | B31: Information exchange between a CB and its clients | C31: The CB informs clients of certification requirements, changes and audit findings; clients inform the CB of significant changes (scope, ownership, incidents, legal proceedings). | D31: Establish a channel to notify the CB of significant changes (e.g. major security incidents, scope/organizational changes, new AI systems) and receive CB updates. | E31: ISO 27001 A.5.5, A.5.24-A.5.26; ISO 42001 A.8.4, 4.3 | F31: ● | G31: ● | I31: Exchanged findings, incident and scope information is sensitive and must remain accurate and confidential. | J31: Change-notification procedure, CB correspondence log | K31: Yes | L31: Not started
A32: Clause 9 | B32: Process requirements
A33: 9.1 | B33: Pre-certification activities | C33: Application review, audit programme, audit time determination, multi-site sampling, and combined audits are defined before certification. | D33: Provide accurate scope, sites, headcount, systems and (for AI) AI systems in scope; agree audit programme and time. | E33: ISO 27001 / 42001 4.3 (scope), 6.1.3 (SoA) | I33: None - process/governance requirement without a direct CIA-protection function. | J33: Application, scope statement, SoA | K33: Yes | L33: Not started
A34: 9.2 | B34: Planning audits | C34: The CB determines audit objectives, scope and criteria, selects the audit team, and prepares an audit plan; plan is communicated to the client. | D34: Review the audit plan; ensure interviewees, evidence and system access are arranged. | E34: ISO 27001 / 42001 9.2 | I34: None - process/governance requirement without a direct CIA-protection function. | J34: Audit plan acknowledged, interviewee schedule | K34: Yes | L34: Not started
A35: 9.3 | B35: Initial certification audit (Stage 1 and Stage 2) | C35: Stage 1 reviews documented information and readiness; Stage 2 assesses implementation and effectiveness of the management system. | D35: Have documented information, risk assessment, SoA, internal audit and management review completed before Stage 1; controls operating with evidence before Stage 2. | E35: ISO 27001 / 42001 clauses 4-10 (tabs 1, 2, 7 in this workbook) | I35: None - process/governance requirement without a direct CIA-protection function. | J35: Stage 1 documentation pack, Stage 2 operating evidence | K35: Yes | L35: Not started
A36: 9.4 | B36: Conducting audits | C36: Opening/closing meetings, evidence gathering and verification, recording findings (nonconformities and opportunities for improvement), audit report, cause analysis of nonconformities and verification of corrections/corrective actions. | D36: Provide access and evidence; agree findings; submit cause analysis and corrective action plans within CB timelines. | E36: ISO 27001 / 42001 10.2 (nonconformity and corrective action) | I36: None - process/governance requirement without a direct CIA-protection function. | J36: Audit evidence, corrective action plans, root-cause analyses | K36: Yes | L36: Not started
A37: 9.5 | B37: Certification decision | C37: Decision is made by persons not involved in the audit, based on audit report and other information; certification granted, refused or deferred. | D37: Do not expect a decision at the closing meeting; ensure all major nonconformities are closed within required time. | E37: - | G37: ● | I37: The decision must rest on accurate, untampered audit information and impartial review. | J37: Nonconformity closure evidence | K37: Yes | L37: Not started
A38: 9.6 | B38: Maintaining certification | C38: Surveillance audits, recertification audits, special audits and suspension/withdrawal processes maintain certification over the cycle. | D38: Keep the ISMS/AIMS operating between audits: internal audits, management reviews, incident handling and change control must continue; prepare for surveillance. | E38: ISO 27001 / 42001 9.1, 9.2, 9.3, 10.1 | I38: None - process/governance requirement without a direct CIA-protection function. | J38: Surveillance-cycle plan, internal audit and management review records | K38: Yes | L38: Not started
A39: 9.7 | B39: Appeals | C39: The CB has a documented process to receive, evaluate and decide appeals; appeal decisions do not lead to discrimination. | D39: Know the appeals process if you disagree with a certification decision. | E39: - | I39: None - process/governance requirement without a direct CIA-protection function. | J39: Appeals procedure reference | K39: Yes | L39: Not started
A40: 9.8 | B40: Complaints | C40: The CB handles complaints about its own activities and about certified clients, with confidentiality. | D40: Be prepared to respond if a complaint concerns your certified system; maintain your own complaints/incident handling. | E40: ISO 27001 A.6.8, A.5.24-A.5.26; ISO 42001 A.3.3, A.8.3 | I40: None - process/governance requirement without a direct CIA-protection function. | J40: Complaints/concerns handling procedure and log | K40: Yes | L40: Not started
A41: 9.9 | B41: Client records | C41: The CB maintains records of audit and certification for all clients, kept confidential and retained per policy. | D41: Retain your own copies of audit reports, findings and closure evidence; treat them as confidential. | E41: ISO 27001 A.5.33, 7.5.3; ISO 42001 7.5.3 | F41: ● | G41: ● | H41: ● | I41: Audit and certification records hold sensitive findings; they must be protected (C), accurate (I) and available for the certification cycle (A). | J41: Records retention and access-control rules for audit records | K41: Yes | L41: Not started
A42: Clause 10 | B42: Management system requirements for certification bodies
A43: 10.1 | B43: Options | C43: The CB implements a management system per Option A (own requirements) or Option B (ISO 9001). | D43: Informational: the CB's own management system is audited by its accreditation body. | E43: - | I43: None - process/governance requirement without a direct CIA-protection function. | J43: - | K43: Yes | L43: Not started
A44: 10.2.1 | B44: Option A - General | C44: The CB establishes, documents, implements and maintains a management system capable of consistent achievement of its requirements. | D44: Informational for clients. | E44: - | I44: None - process/governance requirement without a direct CIA-protection function. | J44: - | K44: Yes | L44: Not started
A45: 10.2.2 | B45: Option A - Management system manual | C45: Documents the management system policies and procedures. | D45: Informational for clients. | E45: - | I45: None - process/governance requirement without a direct CIA-protection function. | J45: - | K45: Yes | L45: Not started
A46: 10.2.3 | B46: Option A - Control of documents | C46: Controls documents so current versions are available and obsolete ones are prevented from use. | D46: Mirrors your own documented-information control; apply the same discipline to your ISMS/AIMS documents. | E46: ISO 27001 / 42001 7.5.3 | G46: ● | I46: Document control preserves integrity of policies and procedures. | J46: Document control procedure and register | K46: Yes | L46: Not started
A47: 10.2.4 | B47: Option A - Control of records | C47: Maintains records demonstrating conformity, protected, retrievable and retained. | D47: Mirrors your own records control; audit evidence must be retrievable and reliable. | E47: ISO 27001 A.5.33; ISO 27001 / 42001 7.5.3 | G47: ● | H47: ● | I47: Records must stay unaltered (I) and retrievable for audit (A). | J47: Records retention schedule, backups of evidence | K47: Yes | L47: Not started
A48: 10.2.5 | B48: Option A - Management review | C48: Top management reviews the CB's management system at planned intervals. | D48: Mirrors your own management review requirement. | E48: ISO 27001 / 42001 9.3 | I48: None - process/governance requirement without a direct CIA-protection function. | J48: Management review minutes | K48: Yes | L48: Not started
A49: 10.2.6 | B49: Option A - Internal audits | C49: The CB conducts internal audits at planned intervals. | D49: Mirrors your own internal audit requirement; CBs expect one completed before the initial audit. | E49: ISO 27001 / 42001 9.2 | I49: None - process/governance requirement without a direct CIA-protection function. | J49: Internal audit reports | K49: Yes | L49: Not started
A50: 10.2.7 | B50: Option A - Corrective actions | C50: The CB identifies and manages nonconformities and takes corrective action. | D50: Mirrors your nonconformity/corrective action process. | E50: ISO 27001 / 42001 10.2 | I50: None - process/governance requirement without a direct CIA-protection function. | J50: Corrective action log | K50: Yes | L50: Not started
A51: 10.2.8 | B51: Option A - Preventive actions | C51: The CB takes actions to eliminate causes of potential nonconformities (risk-based). | D51: Mirrors risk-based preventive thinking in your risk treatment. | E51: ISO 27001 / 42001 6.1, 10.1 | I51: None - process/governance requirement without a direct CIA-protection function. | J51: Preventive action/improvement records | K51: Yes | L51: Not started
A52: 10.3 | B52: Option B - Management system per ISO 9001 | C52: The CB may instead implement a quality management system per ISO 9001. | D52: Informational for clients. | E52: - | I52: None - process/governance requirement without a direct CIA-protection function. | J52: - | K52: Yes | L52: Not started

Sheet 9 GDPR
A1: GDPR (Regulation (EU) 2016/679) - Article Checklist, with CIA-Security Marking
A3: Article | B3: Title | C3: Requirement | D3: C | E3: I | F3: A | G3: Security note / why CIA is involved | H3: Evidence to verify | I3: Applicable | J3: Status | K3: Owner | L3: Notes / Gap
A4: Chapter I | B4: General provisions
A5: Art.2-3 | B5: Material and territorial scope | C5: Determine applicability: processing of personal data wholly/partly by automated means, and territorial scope incl. non-EU controllers/processors offering goods/services to or monitoring EU data subjects. | G5: None - rights-based, procedural or governance obligation without a direct CIA-protection function. | H5: Applicability assessment | I5: Yes | J5: Not started
A6: Art.4 | B6: Definitions | C6: Apply GDPR definitions consistently (personal data, processing, controller, processor, consent, special categories, pseudonymisation, etc.). | G6: None - rights-based, procedural or governance obligation without a direct CIA-protection function. | H6: Glossary/definitions mapping | I6: Yes | J6: Not started
A7: Chapter II | B7: Principles
A8: Art.5(1) | B8: Principles relating to processing | C8: Process personal data lawfully, fairly, transparently; for specified/legitimate purposes; data minimisation; accuracy; storage limitation; integrity and confidentiality; and demonstrate compliance (accountability). | D8: ● | E8: ● | G8: 'Integrity and confidentiality' is an explicit principle: personal data must be processed with appropriate security against unauthorised/unlawful processing, accidental loss, destruction or damage. | H8: Data protection policy covering all principles | I8: Yes | J8: Not started
A9: Art.5(2) | B9: Accountability | C9: The controller is responsible for, and must be able to demonstrate, compliance with the principles. | G9: None - rights-based, procedural or governance obligation without a direct CIA-protection function. | H9: Records of processing, policies, evidence of compliance mechanisms | I9: Yes | J9: Not started
A10: Art.6 | B10: Lawfulness of processing | C10: Identify and document a valid legal basis for each processing activity (consent, contract, legal obligation, vital interests, public task, legitimate interests). | G10: None - rights-based, procedural or governance obligation without a direct CIA-protection function. | H10: Legal basis register | I10: Yes | J10: Not started
A11: Art.7 | B11: Conditions for consent | C11: Where relying on consent, ensure it is freely given, specific, informed, unambiguous, demonstrable, and as easy to withdraw as to give. | G11: None - rights-based, procedural or governance obligation without a direct CIA-protection function. | H11: Consent capture/withdrawal mechanism, consent records | I11: Yes | J11: Not started
A12: Art.8 | B12: Conditions for children's consent | C12: Apply age-of-consent rules for information society services offered directly to children, incl. parental consent verification where required. | G12: None - rights-based, procedural or governance obligation without a direct CIA-protection function. | H12: Age-verification/parental-consent process | I12: Yes | J12: Not started
A13: Art.9 | B13: Special categories of personal data | C13: Do not process special-category data (health, biometric, genetic, racial/ethnic origin, etc.) unless an Article 9(2) condition applies; apply enhanced safeguards. | D13: ● | G13: Special-category data needs enhanced confidentiality safeguards given the higher sensitivity/harm from disclosure. | H13: Special-category processing register and conditions relied on | I13: Yes | J13: Not started
A14: Art.10 | B14: Processing of criminal conviction/offence data | C14: Only process such data under official authority or with appropriate safeguards. | D14: ● | G14: Sensitive data requiring confidentiality safeguards. | H14: Legal basis and safeguards for criminal-data processing | I14: Yes | J14: Not started
A15: Chapter III | B15: Rights of the data subject
A16: Art.12-14 | B16: Transparency and information to data subjects | C16: Provide concise, transparent, intelligible information about processing (privacy notices) at the point of collection or within required timeframes. | G16: None - rights-based, procedural or governance obligation without a direct CIA-protection function. | H16: Privacy notices, layered information | I16: Yes | J16: Not started
A17: Art.15 | B17: Right of access | C17: Provide data subjects, on request, confirmation of processing and a copy of their personal data plus specified information, within one month. | G17: None - rights-based, procedural or governance obligation without a direct CIA-protection function. | H17: Subject access request (SAR) procedure and log | I17: Yes | J17: Not started
A18: Art.16 | B18: Right to rectification | C18: Allow data subjects to have inaccurate personal data corrected without undue delay. | E18: ● | G18: Correcting inaccurate data restores the integrity of the personal data held. | H18: Rectification request procedure | I18: Yes | J18: Not started
A19: Art.17 | B19: Right to erasure ('right to be forgotten') | C19: Erase personal data without undue delay where a listed ground applies (no longer necessary, consent withdrawn, unlawful processing, etc.), subject to exemptions. | G19: None - rights-based, procedural or governance obligation without a direct CIA-protection function. | H19: Erasure request procedure, deletion evidence | I19: Yes | J19: Not started
A20: Art.18 | B20: Right to restriction of processing | C20: Restrict processing in specified circumstances (e.g. accuracy contested, processing unlawful) while a matter is resolved. | G20: None - rights-based, procedural or governance obligation without a direct CIA-protection function. | H20: Restriction-marking mechanism in systems | I20: Yes | J20: Not started
A21: Art.19 | B21: Notification obligation re rectification/erasure/restriction | C21: Notify each recipient to whom data was disclosed of rectification/erasure/restriction, unless impossible or disproportionate. | G21: None - rights-based, procedural or governance obligation without a direct CIA-protection function. | H21: Recipient notification records | I21: Yes | J21: Not started
A22: Art.20 | B22: Right to data portability | C22: Provide personal data in a structured, commonly used, machine-readable format and enable transmission to another controller where technically feasible. | G22: None - rights-based, procedural or governance obligation without a direct CIA-protection function. | H22: Data export/portability mechanism | I22: Yes | J22: Not started
A23: Art.21 | B23: Right to object | C23: Allow objection to processing based on legitimate interests/public task, and to direct marketing (absolute right). | G23: None - rights-based, procedural or governance obligation without a direct CIA-protection function. | H23: Objection-handling procedure, marketing opt-out | I23: Yes | J23: Not started
A24: Art.22 | B24: Automated individual decision-making, including profiling | C24: Do not base decisions with legal/similarly significant effect solely on automated processing (incl. profiling) unless an exception applies; provide safeguards incl. human intervention and right to contest. | G24: None - rights-based, procedural or governance obligation without a direct CIA-protection function. | H24: AI/automated-decision inventory, human-in-the-loop safeguards | I24: Yes | J24: Not started
A25: Chapter IV S1 | B25: Controller and processor obligations
A26: Art.24 | B26: Responsibility of the controller | C26: Implement appropriate technical and organisational measures to ensure and demonstrate processing complies with the Regulation, proportionate to risk. | D26: ● | E26: ● | F26: ● | G26: Foundational obligation to implement security/organisational measures protecting personal data across CIA. | H26: TOM (technical and organisational measures) documentation | I26: Yes | J26: Not started
A27: Art.25 | B27: Data protection by design and by default | C27: Implement data protection principles (e.g. pseudonymisation, minimisation) by design at the time of determining processing means, and by default ensure only necessary data is processed. | D27: ● | G27: Minimisation and pseudonymisation by design/default directly reduce confidentiality exposure. | H27: Privacy-by-design records, default settings review | I27: Yes | J27: Not started
A28: Art.26 | B28: Joint controllers | C28: Determine and transparently document respective responsibilities of joint controllers via an arrangement. | G28: None - rights-based, procedural or governance obligation without a direct CIA-protection function. | H28: Joint-controller arrangement | I28: Yes | J28: Not started
A29: Art.27 | B29: Representatives of controllers/processors not established in the Union | C29: Designate an EU representative where required by territorial scope. | G29: None - rights-based, procedural or governance obligation without a direct CIA-protection function. | H29: Representative appointment | I29: Yes | J29: Not started
A30: Art.28 | B30: Processor | C30: Use only processors providing sufficient guarantees; govern processing via a binding contract (DPA) covering subject matter, duration, nature, purpose, data types, obligations incl. security, sub-processor rules, and audit rights. | D30: ● | E30: ● | F30: ● | G30: DPAs must require the processor to implement Article 32 security measures protecting confidentiality, integrity and availability of the data it processes. | H30: Data processing agreements (DPAs) with all processors | I30: Yes | J30: Not started
A31: Art.29 | B31: Processing under the authority of the controller or processor | C31: Ensure persons processing data under the controller's/processor's authority do so only on instructions, unless required by law. | D31: ● | G31: Limits who can access personal data, protecting confidentiality. | H31: Access authorisation and instruction records | I31: Yes | J31: Not started
A32: Art.30 | B32: Records of processing activities | C32: Maintain records of processing activities (ROPA) covering purposes, categories of data/subjects, recipients, transfers, retention periods and security measures. | G32: None - rights-based, procedural or governance obligation without a direct CIA-protection function. | H32: ROPA | I32: Yes | J32: Not started
A33: Art.31 | B33: Cooperation with the supervisory authority | C33: Cooperate with the supervisory authority on request in the performance of its tasks. | G33: None - rights-based, procedural or governance obligation without a direct CIA-protection function. | H33: Regulator engagement procedure | I33: Yes | J33: Not started
A34: Chapter IV S2 | B34: Security of personal data
A35: Art.32 | B35: Security of processing | C35: Implement appropriate technical and organisational measures to ensure a level of security appropriate to risk: pseudonymisation/encryption; ongoing confidentiality, integrity, availability and resilience of systems; ability to restore availability/access after an incident; regular testing/evaluation of measures. | D35: ● | E35: ● | F35: ● | G35: This is GDPR's core cybersecurity article - it explicitly names confidentiality, integrity, availability and resilience as the required security outcomes. | H35: Security policy, encryption/pseudonymisation controls, resilience/DR testing, security testing reports | I35: Yes | J35: Not started
A36: Art.33 | B36: Notification of a personal data breach to the supervisory authority | C36: Notify the supervisory authority without undue delay, and where feasible within 72 hours, of becoming aware of a personal data breach, unless unlikely to result in risk; document all breaches. | D36: ● | E36: ● | F36: ● | G36: Breach response protects against further loss of confidentiality/integrity/availability and is triggered specifically by CIA-impacting events. | H36: Breach notification procedure, breach register, notifications sent | I36: Yes | J36: Not started
A37: Art.34 | B37: Communication of a personal data breach to the data subject | C37: Communicate the breach to affected data subjects without undue delay when it is likely to result in a high risk to their rights and freedoms. | D37: ● | E37: ● | F37: ● | G37: Follows directly from a confidentiality/integrity/availability-impacting breach. | H37: Data-subject breach notifications, risk assessment of breach | I37: Yes | J37: Not started
A38: Chapter IV S3 | B38: Data protection impact assessment and prior consultation
A39: Art.35 | B39: Data protection impact assessment (DPIA) | C39: Carry out a DPIA before processing likely to result in high risk to individuals (e.g. large-scale special-category processing, systematic monitoring, new technology incl. AI); describe processing, necessity/proportionality, risks, and measures to address them. | D39: ● | G39: DPIAs must assess and mitigate confidentiality/privacy risks to individuals from the processing. | H39: DPIA reports | I39: Yes | J39: Not started
A40: Art.36 | B40: Prior consultation | C40: Consult the supervisory authority prior to processing where a DPIA indicates high residual risk that cannot be mitigated. | G40: None - rights-based, procedural or governance obligation without a direct CIA-protection function. | H40: Prior consultation records where applicable | I40: Yes | J40: Not started
A41: Chapter IV S4 | B41: Data protection officer
A42: Art.37 | B42: Designation of the data protection officer | C42: Designate a DPO where required (public authority, large-scale regular/systematic monitoring, or large-scale special-category processing); publish contact details and notify the supervisory authority. | G42: None - rights-based, procedural or governance obligation without a direct CIA-protection function. | H42: DPO appointment record, published contact details | I42: Yes | J42: Not started
A43: Art.38 | B43: Position of the DPO | C43: Involve the DPO properly and in a timely manner in all data protection matters; provide resources and independence; DPO reports to highest management level. | G43: None - rights-based, procedural or governance obligation without a direct CIA-protection function. | H43: DPO involvement records, resourcing evidence | I43: Yes | J43: Not started
A44: Art.39 | B44: Tasks of the DPO | C44: DPO informs/advises on obligations, monitors compliance, advises on DPIAs, cooperates with and acts as contact point for the supervisory authority. | G44: None - rights-based, procedural or governance obligation without a direct CIA-protection function. | H44: DPO activity records | I44: Yes | J44: Not started
A45: Chapter V | B45: Transfers of personal data to third countries or international organisations
A46: Art.44-45 | B46: General principle for transfers / adequacy decisions | C46: Transfer personal data outside the EEA only where an adequacy decision applies or another Chapter V mechanism is used. | G46: None - rights-based, procedural or governance obligation without a direct CIA-protection function. | H46: Transfer mechanism register | I46: Yes | J46: Not started
A47: Art.46 | B47: Transfers subject to appropriate safeguards | C47: Absent adequacy, use appropriate safeguards (e.g. Standard Contractual Clauses, Binding Corporate Rules) providing enforceable rights and effective remedies. | D47: ● | G47: Cross-border transfer safeguards protect confidentiality of personal data once it leaves the EEA's legal protections. | H47: Signed SCCs/BCRs, transfer impact assessments | I47: Yes | J47: Not started
A48: Art.49 | B48: Derogations for specific situations | C48: Rely on derogations (explicit consent, contract necessity, public interest, etc.) only where Article 46 mechanisms are unavailable and conditions are met. | G48: None - rights-based, procedural or governance obligation without a direct CIA-protection function. | H48: Derogation justification records | I48: Yes | J48: Not started
A49: Chapter VIII | B49: Remedies, liability and penalties
A50: Art.82 | B50: Right to compensation and liability | C50: Data subjects have the right to compensation for material or non-material damage from an infringement; controllers/processors are liable unless not responsible for the event. | G50: None - rights-based, procedural or governance obligation without a direct CIA-protection function. | H50: Liability/insurance review | I50: Yes | J50: Not started
A51: Art.83 | B51: Administrative fines | C51: Ensure compliance to avoid fines (tiered, up to the higher of EUR 20m or 4% of global annual turnover for the most serious infringements). | G51: None - rights-based, procedural or governance obligation without a direct CIA-protection function. | H51: Compliance/legal risk register | I51: Yes | J51: Not started

Sheet 10 OWASP LLM Top 10
A1: OWASP Top 10 for LLM Applications 2025 (v2.0) - Risk Checklist, with CIA Marking
A3: Ref | B3: Risk | C3: Description | D3: Mitigations | E3: C | F3: I | G3: A | H3: Why CIA is involved | I3: Evidence to verify | J3: Applicable | K3: Status | L3: Owner | M3: Notes / Gap
A4: LLM01:2025 | B4: Prompt Injection | C4: Crafted inputs (direct or indirect, via untrusted content the model retrieves/ingests) override or manipulate the model's instructions, causing unintended actions, data exposure or policy violations. | D4: Enforce privilege control on LLM access to backend systems; segregate/mark external content; require human approval for high-risk actions; adversarial/red-team testing; input/output filtering. | E4: ● | F4: ● | G4: ● | H4: Can be used to exfiltrate data (C), manipulate outputs/actions (I), or trigger disruptive/unbounded actions (A) depending on what the model is connected to. | I4: Test reports / control evidence for this risk | J4: Yes | K4: Not started
A5: LLM02:2025 | B5: Sensitive Information Disclosure | C5: The model inadvertently exposes PII, credentials, proprietary data or confidential business information present in training data, context or connected systems. | D5: Data sanitization/redaction; strict access controls on data the model can reach; differential privacy/federated learning where applicable; conceal system prompts; output filtering for sensitive patterns. | E5: ● | H5: Direct confidentiality risk - unauthorized disclosure of sensitive data through model output. | I5: Test reports / control evidence for this risk | J5: Yes | K5: Not started
A6: LLM03:2025 | B6: Supply Chain | C6: Compromised or vulnerable components in the LLM supply chain - pre-trained models, fine-tuning adapters (e.g. LoRA), datasets, plugins and deployment platforms - introduce vulnerabilities, backdoors or bias. | D6: Vet data/model sources and suppliers; vulnerability scanning of models/dependencies; maintain an AI/ML Bill of Materials (SBOM/MLBOM); use verifiable model provenance and integrity checks; monitor collaborative development platforms. | E6: ● | F6: ● | G6: ● | H6: A compromised supply-chain component can leak data (C), alter model behaviour (I) or disable the service (A). | I6: Test reports / control evidence for this risk | J6: Yes | K6: Not started
A7: LLM04:2025 | B7: Data and Model Poisoning | C7: Manipulation of training, fine-tuning or embedding data introduces vulnerabilities, backdoors or biases that compromise the model's security, effectiveness or ethical behaviour. | D7: Track data lineage/provenance; vet data vendors; strict sandboxing of training pipelines; use data version control (DVC); red-team for poisoning; monitor training loss/behaviour for anomalies. | F7: ● | H7: Poisoning directly corrupts the integrity of the model's learned behaviour. | I7: Test reports / control evidence for this risk | J7: Yes | K7: Not started
A8: LLM05:2025 | B8: Improper Output Handling | C8: Insufficient validation, sanitization or escaping of LLM output before it is passed to downstream systems, enabling XSS, CSRF, SSRF, privilege escalation or remote code execution. | D8: Treat model output as untrusted input; apply context-aware output encoding/sanitization; validate before executing/rendering; least-privilege execution of any downstream action. | F8: ● | G8: ● | H8: Unvalidated output can corrupt downstream systems (I) or be used to trigger disruptive actions (A) via the systems that consume it. | I8: Test reports / control evidence for this risk | J8: Yes | K8: Not started
A9: LLM06:2025 | B9: Excessive Agency | C9: An LLM-based agent is granted excessive functionality, permissions or autonomy, allowing it to take damaging actions beyond what the task requires, especially when combined with prompt injection. | D9: Apply least-privilege scoping of tools/functions/plugins; require human approval for consequential actions; limit autonomous action chains; log and monitor agent actions; use sandboxed execution environments. | E9: ● | F9: ● | G9: ● | H9: An over-privileged agent can be manipulated into unauthorized disclosure (C), unintended changes (I) or destructive/disruptive actions (A). | I9: Test reports / control evidence for this risk | J9: Yes | K9: Not started
A10: LLM07:2025 | B10: System Prompt Leakage | C10: Attackers extract the hidden system prompt, exposing internal instructions, business logic, credentials or guardrail design that can then be used to bypass safeguards. | D10: Avoid placing secrets/credentials in system prompts; treat system prompts as sensitive but not as a security boundary; use out-of-band guardrails independent of the prompt; test for extraction via red-teaming. | E10: ● | H10: Direct confidentiality risk to the operator's internal instructions and any embedded secrets. | I10: Test reports / control evidence for this risk | J10: Yes | K10: Not started
A11: LLM08:2025 | B11: Vector and Embedding Weaknesses | C11: Weaknesses in how vectors/embeddings are generated, stored, or retrieved (e.g. in RAG pipelines) allow injection of malicious content, data poisoning of the knowledge base, or unauthorized retrieval of restricted data. | D11: Apply access controls/permissions on the vector store per document sensitivity; validate/sanitize ingested content before embedding; monitor retrieval patterns; isolate multi-tenant vector stores. | E11: ● | F11: ● | H11: Retrieval-store weaknesses can expose data across access boundaries (C) or let injected content corrupt retrieved context (I). | I11: Test reports / control evidence for this risk | J11: Yes | K11: Not started
A12: LLM09:2025 | B12: Misinformation | C12: The model produces confident but false or misleading output (hallucination), which users or downstream systems may treat as reliable, leading to harmful decisions, legal exposure or reputational damage. | D12: Ground outputs with retrieval/citation (RAG) and require source attribution; implement automated fact-checking/cross-verification; communicate limitations to users; human review for high-stakes outputs. | F12: ● | H12: Misinformation is fundamentally an integrity failure - the output does not reliably reflect truth or the intended knowledge base. | I12: Test reports / control evidence for this risk | J12: Yes | K12: Not started
A13: LLM10:2025 | B13: Unbounded Consumption | C13: Uncontrolled or excessive inference requests (denial of wallet/service, resource exhaustion) degrade availability or cause uncontrolled cost, incl. via model extraction through repeated querying. | D13: Rate limiting and quotas per user/API key; input/output size limits; monitor for abnormal usage patterns; cost alerting and circuit breakers; watermarking/output limits to deter model extraction. | G13: ● | H13: Directly an availability and resource-exhaustion risk, with a confidentiality dimension when used for model extraction. | I13: Test reports / control evidence for this risk | J13: Yes | K13: Not started

Sheet 11 ISO 27701 PIMS
A1: ISO/IEC 27701:2019 - Privacy Information Management System (PIMS) Checklist, with CIA Marking
A3: Ref | B3: Title | C3: Requirement / guidance | D3: C | E3: I | F3: A | G3: Why CIA is involved | H3: Evidence to verify | I3: Applicable | J3: Status | K3: Owner | L3: Notes / Gap
A4: Clause 5 | B4: PIMS-specific requirements related to ISO/IEC 27001 (extends ISMS clauses 4-10 to privacy)
A5: 5.2 | B5: Context of the organization (privacy extension) | C5: Extend ISO 27001 4.1-4.4 to consider the organization's role (PII controller and/or processor), applicable privacy laws/regulations (e.g. GDPR, PDPPL), and interested parties relevant to PII processing. | G5: None - privacy governance/rights-based requirement without a direct CIA-protection function. | H5: PIMS scope statement identifying controller/processor role(s) and applicable privacy law | I5: Yes | J5: Not started
A6: 5.3 | B6: Leadership (privacy extension) | C6: Extend ISO 27001 5.1-5.3 so the information security policy is extended (or a separate privacy policy established) with privacy roles and responsibilities assigned. | G6: None - privacy governance/rights-based requirement without a direct CIA-protection function. | H6: Privacy policy, PIMS roles/RACI | I6: Yes | J6: Not started
A7: 5.4 | B7: Planning (privacy extension) - privacy risk assessment | C7: Extend the ISO 27001 risk assessment (6.1.2) to consider risks associated with the processing of PII to both the organization and to PII principals; extend risk treatment (6.1.3) and produce a PIMS Statement of Applicability referencing Annex A/B. | D7: ● | G7: Privacy risk assessment specifically evaluates confidentiality/exposure risk to individuals from PII processing. | H7: Privacy risk assessment methodology and register, PIMS SoA | I7: Yes | J7: Not started
A8: 5.5 | B8: Support (privacy extension) | C8: Extend ISO 27001 7.x so resources, competence, awareness, communication and documented information also cover the PIMS. | G8: None - privacy governance/rights-based requirement without a direct CIA-protection function. | H8: Privacy training records, PIMS documentation set | I8: Yes | J8: Not started
A9: 5.6 | B9: Operation (privacy extension) | C9: Extend ISO 27001 8.1-8.3 operational planning/control and risk assessment/treatment to privacy risks arising from operating the PIMS. | G9: None - privacy governance/rights-based requirement without a direct CIA-protection function. | H9: PIMS operating procedures | I9: Yes | J9: Not started
A10: 5.7 | B10: Performance evaluation (privacy extension) | C10: Extend ISO 27001 9.1-9.3 monitoring, internal audit and management review to cover PIMS conformity and effectiveness. | G10: None - privacy governance/rights-based requirement without a direct CIA-protection function. | H10: PIMS-inclusive internal audit and management review records | I10: Yes | J10: Not started
A11: 5.8 | B11: Improvement (privacy extension) | C11: Extend ISO 27001 10.1-10.2 continual improvement and corrective action to nonconformities affecting the PIMS. | G11: None - privacy governance/rights-based requirement without a direct CIA-protection function. | H11: PIMS nonconformity/CAPA records | I11: Yes | J11: Not started
A12: Clause 6 | B12: PIMS-specific guidance related to ISO/IEC 27002 controls (privacy overlay on the 93 security controls)
A13: 6.O | B13: Organizational controls - privacy guidance | C13: Apply privacy-specific guidance to organizational controls (e.g. policies, asset inventory to include PII inventory, classification of PII, supplier/third-party PII processing terms, incident management covering PII breaches). | D13: ● | G13: Extends organizational security controls specifically to protect the confidentiality of PII. | H13: PII asset/data inventory, supplier PII clauses, PII breach procedure | I13: Yes | J13: Not started
A14: 6.P | B14: People controls - privacy guidance | C14: Apply privacy-specific guidance to people controls (e.g. screening, terms of employment, awareness/training on PII handling, confidentiality obligations). | G14: None - privacy governance/rights-based requirement without a direct CIA-protection function. | H14: PII-specific confidentiality agreements/training | I14: Yes | J14: Not started
A15: 6.Ph | B15: Physical controls - privacy guidance | C15: Apply privacy-specific guidance to physical controls (e.g. secure areas/media handling where PII is stored or processed physically). | G15: None - privacy governance/rights-based requirement without a direct CIA-protection function. | H15: Physical control review for locations holding PII | I15: Yes | J15: Not started
A16: 6.T | B16: Technological controls - privacy guidance | C16: Apply privacy-specific guidance to technological controls (e.g. access control, cryptography, data masking/de-identification, deletion, logging) specifically for systems processing PII. | D16: ● | E16: ● | G16: Technical controls (encryption, masking, access control, deletion) directly protect confidentiality and integrity of PII. | H16: Technical control mapping to PII systems (encryption, masking, deletion) | I16: Yes | J16: Not started
A17: Clause 7 | B17: Additional ISO/IEC 27002 guidance for PII controllers
A18: 7.2 | B18: Conditions for collection and processing | C18: Identify and document the lawful basis for processing, ensure PII is collected/processed only for identified, specific, explicit and legitimate purposes; determine and comply with obligations to PII principals; obtain/record consent where relied upon; conduct privacy impact assessments where required. | G18: None - privacy governance/rights-based requirement without a direct CIA-protection function. | H18: Legal basis register, consent records, PIA/DPIA reports | I18: Yes | J18: Not started
A19: 7.3 | B19: Obligations to PII principals | C19: Provide transparent information to PII principals; support their rights (access, correction, erasure, objection); establish mechanisms for requests and complaints; handle automated decision-making per policy. | G19: None - privacy governance/rights-based requirement without a direct CIA-protection function. | H19: Privacy notices, data-subject rights procedure and request log | I19: Yes | J19: Not started
A20: 7.4 | B20: Privacy by design and privacy by default | C20: Limit collection/processing to what is adequate, relevant and limited to purpose (minimisation); de-identify/delete PII when no longer needed; ensure PII disposal at end of retention; design temporary files and system-generated data to protect privacy. | D20: ● | G20: Minimisation, de-identification and deletion directly reduce confidentiality exposure of PII. | H20: Privacy-by-design records, retention/deletion schedule, temp-file handling policy | I20: Yes | J20: Not started
A21: 7.5 | B21: PII sharing, transfer and disclosure | C21: Identify the basis for transfers between jurisdictions/organizations; document and communicate applicable transfer mechanisms; record and manage disclosures to third parties, incl. legally mandated disclosures. | D21: ● | G21: Controls over sharing/transfer/disclosure directly govern who may access PII and under what safeguards. | H21: Transfer/disclosure register, cross-border transfer mechanism records (e.g. SCCs) | I21: Yes | J21: Not started
A22: Clause 8 | B22: Additional ISO/IEC 27002 guidance for PII processors
A23: 8.2 | B23: Conditions for collection and processing | C23: Process PII only per documented instructions of the controller (incl. for transfers); ensure the contract with the controller addresses PII processing; assist the controller in fulfilling its obligations. | G23: None - privacy governance/rights-based requirement without a direct CIA-protection function. | H23: Processing agreement (DPA), documented controller instructions | I23: Yes | J23: Not started
A24: 8.3 | B24: Obligations to PII principals | C24: Assist the controller in providing information to and fulfilling the rights of PII principals, per contract; do not respond directly to PII principals unless authorized. | G24: None - privacy governance/rights-based requirement without a direct CIA-protection function. | H24: Processor support procedure for data-subject rights requests | I24: Yes | J24: Not started
A25: 8.4 | B25: Privacy by design and privacy by default | C25: Apply temporary files/data minimisation, retention/return/disposal of PII at contract end or on instruction, and ensure sub-processing arrangements uphold the same privacy protections. | D25: ● | G25: Return/disposal at contract end and sub-processor flow-down protect confidentiality of PII across the processing chain. | H25: Sub-processor register and flow-down clauses, end-of-contract deletion/return evidence | I25: Yes | J25: Not started
A26: 8.5 | B26: PII sharing, transfer and disclosure | C26: Notify the controller of legally binding requests for disclosure, of any unauthorized access/breach, and of the use of sub-processors; disclose/transfer PII only per controller instructions and applicable transfer mechanisms. | D26: ● | E26: ● | G26: Breach notification and controlled disclosure protect confidentiality and preserve accountable, unaltered handling of PII. | H26: Sub-processor notifications, breach notification to controller, disclosure records | I26: Yes | J26: Not started
A27: Annex A | B27: PIMS-specific reference controls for PII controllers | C27: Implement the Annex A control set (mapped to the Clause 7 categories above: conditions for collection/processing, obligations to PII principals, privacy by design/default, sharing/transfer/disclosure) as the certifiable controller control objectives, selected via the PIMS risk assessment and SoA. | G27: None - privacy governance/rights-based requirement without a direct CIA-protection function. | H27: Controller SoA with Annex A controls selected/justified | I27: Yes | J27: Not started
A28: Annex B | B28: PIMS-specific reference controls for PII processors | C28: Implement the Annex B control set (mapped to the Clause 8 categories above) as the certifiable processor control objectives, selected via the PIMS risk assessment and SoA. | G28: None - privacy governance/rights-based requirement without a direct CIA-protection function. | H28: Processor SoA with Annex B controls selected/justified | I28: Yes | J28: Not started
A29: Annex C-E | B29: Mapping annexes (ISO/IEC 29100, GDPR, ISO/IEC 27018 and 29151) | C29: Use the informative mapping annexes to cross-reference PIMS controls to the ISO/IEC 29100 privacy framework, GDPR articles, and cloud-PII-specific standards ISO/IEC 27018 and 29151. | G29: None - privacy governance/rights-based requirement without a direct CIA-protection function. | H29: Cross-reference table used for GDPR/29100 alignment (see Tab 9 GDPR) | I29: Yes | J29: Not started

Sheet 12 Master Control List
A1: Master Control List - All 19 Frameworks, Grouped by Common Control Domain
A3: Domain | B3: Framework | C3: Ref | D3: Title | E3: C | F3: I | G3: A | H3: Requirement (condensed) | I3: Applicable | J3: Status | K3: Owner | L3: Notes / Gap
A4: Human Resources Security & Awareness (46 items across 13 frameworks)
A5: Human Resources Security & Awareness | B5: ISO/IEC 42001 | C5: 4.3 | D5: Determining the scope of the AI management system | H5: Determine and document AIMS boundaries and applicability, considering 4.1, 4.2 and the AI systems in scope. | I5: Yes | J5: Not started
A6: Human Resources Security & Awareness | B6: ISO/IEC 42001 | C6: 5.3 | D6: Roles, responsibilities and authorities | H6: Assign and communicate AIMS roles, incl. responsibility for conformity to the standard and reporting AIMS performance to top management. | I6: Yes | J6: Not started
A7: Human Resources Security & Awareness | B7: ISO/IEC 42001 | C7: 7.2 | D7: Competence | H7: Determine necessary competence of persons affecting AI performance; ensure competence via education, training or experience; retain evidence. | I7: Yes | J7: Not started
A8: Human Resources Security & Awareness | B8: ISO/IEC 42001 | C8: 7.3 | D8: Awareness | H8: Ensure persons are aware of the AI policy, their contribution to AIMS effectiveness and consequences of non-conformity. | I8: Yes | J8: Not started
A9: Human Resources Security & Awareness | B9: ISO/IEC 42001 | C9: 7.5.1 | D9: Documented information - General | H9: AIMS includes documented information required by the standard and determined necessary for AIMS effectiveness. | I9: Yes | J9: Not started
A10: Human Resources Security & Awareness | B10: ISO/IEC 42001 | C10: 9.2.1 | D10: Internal audit - General | H10: Conduct internal audits at planned intervals to check AIMS conformity to own requirements and the standard, and effective implementation. | I10: Yes | J10: Not started
A11: Human Resources Security & Awareness | B11: ISO/IEC 42001 | C11: A.6.2.3 | D11: Documentation of AI system design and development | H11: Document design and development per organizational objectives, documented requirements and criteria (architecture, model choices, training approach). | I11: Yes | J11: Not started
A12: Human Resources Security & Awareness | B12: EU AI Act | C12: Art.4 | D12: AI literacy | H12: Take measures to ensure sufficient AI literacy of staff and others dealing with AI systems on the organization's behalf, considering their technical knowledge, experience and context of use. | I12: Yes | J12: Not started
A13: Human Resources Security & Awareness | B13: EU AI Act | C13: Art.22 | D13: Authorised representatives | H13: Non-EU providers appoint an EU authorised representative with a mandate covering conformity documentation, cooperation with authorities and registration duties. | I13: Yes | J13: Not started
A14: Human Resources Security & Awareness | B14: OECD AI Principles | C14: 2.5 | D14: International co-operation for trustworthy AI | H14: Actively co-operate across borders and sectors to advance responsible stewardship of trustworthy AI, incl. common understanding of AI actor obligations, interoperable governance, standards and metrics. | I14: Yes | J14: Not started
A15: Human Resources Security & Awareness | B15: OECD AI Principles | C15: 3.1 | D15: General-purpose and generative AI risks | H15: Address risks specific to general-purpose/foundation and generative AI models, incl. safety, misuse and information-integrity risks (e.g. disinformation, deepfakes). | I15: Yes | J15: Not started
A16: Human Resources Security & Awareness | B16: NIST AI RMF | C16: Govern 2 | D16: Accountability structures are in place so appropriate teams and individuals are empowered, responsible and trained for mapping, measuring and managing AI risks. | H16: Assign clear roles/responsibilities for AI risk management and provide training. | I16: Yes | J16: Not started
... A28: Human Resources Security & Awareness | B28: ISO/IEC 27001 | C28: 6.4 | D28: Disciplinary process | H28: Formalize and communicate a disciplinary process for security policy violations. | I28: Yes | J28: Not started
A29: Human Resources Security & Awareness | B29: ISO/IEC 27001 | C29: 6.6 | D29: Confidentiality or non-disclosure agreements | E29: ● | H29: Identify, document, review and sign NDAs reflecting protection needs. | I29: Yes | J29: Not started
A30: Human Resources Security & Awareness | B30: ISO/IEC 27001 | C30: 6.7 | D30: Remote working | E30: ● | F30: ● | G30: ● | H30: Implement security measures when personnel work remotely. | I30: Yes | J30: Not started
A31: Human Resources Security & Awareness | B31: ISO/IEC 27001 | C31: 8.7 | D31: Protection against malware | F31: ● | G31: ● | H31: Implement malware protection supported by user awareness. | I31: Yes | J31: Not started
A32: Human Resources Security & Awareness | B32: ISO/IEC 17021-1 | C32: 4.1 | D32: General | H32: Certification must inspire confidence: principles of impartiality, competence, responsibility, openness, confidentiality, responsiveness to complaints and risk-based approach underpin all certification activity. | I32: Yes | J32: Not started
A33: Human Resources Security & Awareness | B33: ISO/IEC 17021-1 | C33: 4.3 | D33: Competence | H33: Certification personnel must have the knowledge and skills to perform certification activities for the relevant scope/sector. | I33: Yes | J33: Not started
A34: Human Resources Security & Awareness | B34: ISO/IEC 17021-1 | C34: 4.8 | D34: Risk-based approach | H34: The CB considers risks to impartiality, competence and consistency when planning and decision-making. | I34: Yes | J34: Not started
A35: Human Resources Security & Awareness | B35: ISO/IEC 17021-1 | C35: 7.2 | D35: Personnel involved in certification activities | H35: The CB has sufficient competent personnel (auditors, reviewers, decision-makers); contracts and training are in place. | I35: Yes | J35: Not started
A36: Human Resources Security & Awareness | B36: ISO/IEC 17021-1 | C36: 7.4 | D36: Personnel records | E36: ● | F36: ● | H36: The CB maintains up-to-date records of qualifications, training, experience and performance of personnel. | I36: Yes | J36: Not started
A37: Human Resources Security & Awareness | B37: ISO/IEC 17021-1 | C37: 8.2 | D37: Certification documents | F37: ● | H37: The CB gives certification documents identifying the client, standard, scope, and validity. | I37: Yes | J37: Not started
A38: Human Resources Security & Awareness | B38: ISO/IEC 27701 | C38: 5.5 | D38: Support (privacy extension) | H38: Extend ISO 27001 7.x so resources, competence, awareness, communication and documented information also cover the PIMS. | I38: Yes | J38: Not started
A39: Human Resources Security & Awareness | B39: ISO/IEC 27701 | C39: 6.P | D39: People controls - privacy guidance | H39: Apply privacy-specific guidance to people controls (e.g. screening, terms of employment, awareness/training on PII handling, confidentiality obligations). | I39: Yes | J39: Not started
A40: Human Resources Security & Awareness | B40: ISO/IEC 27701 | C40: Annex C-E | D40: Mapping annexes (ISO/IEC 29100, GDPR, ISO/IEC 27018 and 29151) | H40: Use the informative mapping annexes to cross-reference PIMS controls to the ISO/IEC 29100 privacy framework, GDPR articles, and cloud-PII-specific standards ISO/IEC 27018 and 29151. | I40: Yes | J40: Not started
A41: Human Resources Security & Awareness | B41: Privacy by Design (Cavoukian) | C41: 2.3 | D41: Opt-in, not opt-out, for anything beyond the necessary minimum | H41: Any processing beyond what is strictly necessary (e.g. marketing, analytics, AI training on user data) requires an affirmative, informed choice rather than being pre-enabled. | I41: Yes | J41: Not started
A42: Human Resources Security & Awareness | B42: Privacy by Design (Cavoukian) | C42: 7.3 | D42: Communicate in clear, understandable language | H42: Ensure privacy-related information presented within the design (notices, prompts, settings) is written in plain, non-technical, non-legalistic language appropriate to the audience. | I42: Yes | J42: Not started
A43: Human Resources Security & Awareness | B43: ISO/IEC 31700-1/-2 | C43: 5.5 | D43: Communicating to diverse consumer population | H43: Ensure privacy communications are accessible and understandable across the diversity of the consumer population (language, literacy, disability, age, context of use). | I43: Yes | J43: Not started
A44: Human Resources Security & Awareness | B44: ISO/IEC 31700-1/-2 | C44: 7.2 | D44: Integrating design/operation of privacy controls into product development and management lifecycles | H44: Embed privacy-control design and operation activities into the standard product development and management lifecycle (e.g. stage gates, sprints, release processes), not as a separate parallel track. | I44: Yes | J44: Not started
A45: Human Resources Security & Awareness | B45: ISO/IEC 5181 | C45: AI.4 | D45: Provenance of AI-generated content (related but distinct standard) | H45: Where the AI system generates synthetic content (text, image, audio, video), be aware that content-level provenance/authenticity (e.g. watermarking, C2PA Content Credentials) is addressed by separate, content-focused standards/initiative... | I45: Yes | J45: Not started
A46: Human Resources Security & Awareness | B46: ISO/IEC 27090 | C46: 5.1 | D46: Apply established information security practice as the foundation | E46: ● | F46: ● | G46: ● | H46: Recognize that AI systems run on conventional computer systems/networks, so all the usual confidentiality, integrity and availability/cybersecurity concerns (e.g. ISO 27001/27002, Tab 7) still apply and remain essential - AI-specific thr... | I46: Yes | J46: Not started
A47: Human Resources Security & Awareness | B47: ISO/IEC 27090 | C47: 6.8 | D47: Further threats per the standard's catalogue (12+ scenarios) | H47: Beyond the named threats above, the standard's threat catalogue covers at least a dozen scenarios in total (each with about a page of guidance); review the full published catalogue for scenarios not individually itemised in this tab (e.g... | I47: Yes | J47: Not started
A48: Human Resources Security & Awareness | B48: ISO/IEC 27090 | C48: 7.1 | D48: Apply threat-specific detection and mitigation guidance | E48: ● | F48: ● | G48: ● | H48: For each threat in Clause 6, apply the standard's guidance on characterising the threat, its potential consequences, and how to detect and mitigate it - rather than applying generic security controls uniformly without considering threat-... | I48: Yes | J48: Not started
A49: Human Resources Security & Awareness | B49: ISO/IEC 27090 | C49: Annex C | D49: Federated machine learning | E49: ● | F49: ● | H49: Apply additional considerations for federated learning architectures, where training occurs across distributed data holders without centralising raw data - a different trust and attack-surface model from centralised training. | I49: Yes | J49: Not started
A50: Human Resources Security & Awareness | B50: MITRE ATLAS | C50: TA-06 | D50: Persistence | F50: ● | H50: Adversary maintains a foothold across restarts, retraining or redeployment of the AI system (e.g. a persistent backdoor embedded in a model or pipeline). | I50: Yes | J50: Not started
A51: Governance, Policy & Leadership (42 items across 10 frameworks)
A52: Governance, Policy & Leadership | B52: ISO/IEC 42001 | C52: 4.2 | D52: Understanding the needs and expectations of interested parties | H52: Identify interested parties relevant to the AIMS, their requirements (incl. legal/regulatory, e.g. EU AI Act, PDPPL) and which will be addressed through the AIMS. | I52: Yes | J52: Not started
A53: Governance, Policy & Leadership | B53: ISO/IEC 42001 | C53: 4.4 | D53: AI management system | H53: Establish, implement, maintain and continually improve the AIMS, including needed processes and their interactions. | I53: Yes | J53: Not started
A54: Governance, Policy & Leadership | B54: ISO/IEC 42001 | C54: 5.1 | D54: Leadership and commitment | H54: Top management demonstrates commitment: AI policy and objectives aligned to strategy, AIMS integrated into processes, resources provided, importance of effective AI management communicated, outcomes ensured, improvement promoted. | I54: Yes | J54: Not started
A55: Governance, Policy & Leadership | B55: ISO/IEC 42001 | C55: 6.2 | D55: AI objectives and planning to achieve them | H55: Establish measurable AI objectives at relevant functions/levels, consistent with the AI policy; plan what, resources, owner, deadline and evaluation. | I55: Yes | J55: Not started
A56: Governance, Policy & Leadership | B56: ISO/IEC 42001 | C56: 6.3 | D56: Planning of changes | H56: Carry out AIMS changes in a planned manner when a need for change is determined. | I56: Yes | J56: Not started
A57: Governance, Policy & Leadership | B57: ISO/IEC 42001 | C57: 7.1 | D57: Resources | H57: Determine and provide resources needed to establish, implement, maintain and improve the AIMS. | I57: Yes | J57: Not started
A58: Governance, Policy & Leadership | B58: ISO/IEC 42001 | C58: 7.4 | D58: Communication | H58: Determine internal and external communications relevant to the AIMS: what, when, with whom, how. | I58: Yes | J58: Not started
A59: Governance, Policy & Leadership | B59: ISO/IEC 42001 | C59: A.2.2 | D59: AI policy | H59: Document a policy for the development or use of AI systems. | I59: Yes | J59: Not started
A60: Governance, Policy & Leadership | B60: ISO/IEC 42001 | C60: A.2.3 | D60: Alignment with other organizational policies | H60: Determine where other policies (security, privacy, quality, safety, etc.) are affected by or apply to AI objectives, and align them. | I60: Yes | J60: Not started
A61: Governance, Policy & Leadership | B61: ISO/IEC 42001 | C61: A.2.4 | D61: Review of the AI policy | H61: Review the AI policy at planned intervals or on significant change to ensure continuing suitability, adequacy and effectiveness. | I61: Yes | J61: Not started
A62: Governance, Policy & Leadership | B62: ISO/IEC 42001 | C62: A.8.3 | D62: External reporting | H62: Provide capability for interested parties to report adverse impacts of the AI system. | I62: Yes | J62: Not started
A63: Governance, Policy & Leadership | B63: ISO/IEC 42001 | C63: A.8.5 | D63: Information for interested parties | H63: Determine and document obligations to report information about the AI system to interested parties. | I63: Yes | J63: Not started
... A81: Governance, Policy & Leadership | B81: ISO/IEC 27001 | C81: 5.6 | D81: Contact with special interest groups | H81: Maintain contact with security forums and professional associations. | I81: Yes | J81: Not started
A82: Governance, Policy & Leadership | B82: ISO/IEC 27001 | C82: 5.7 | D82: Threat intelligence | E82: ● | F82: ● | G82: ● | H82: Collect and analyse information on threats to produce threat intelligence. | I82: Yes | J82: Not started
A83: Governance, Policy & Leadership | B83: ISO/IEC 27001 | C83: 5.8 | D83: Information security in project management | H83: Integrate security into project management across all projects. | I83: Yes | J83: Not started
A84: Governance, Policy & Leadership | B84: ISO/IEC 17021-1 | C84: 5.2 | D84: Management of impartiality | H84: The CB identifies, analyses and documents risks to impartiality and has top management commitment to it. | I84: Yes | J84: Not started
A85: Governance, Policy & Leadership | B85: ISO/IEC 17021-1 | C85: 6.1 | D85: Organizational structure and top management | H85: The CB documents its organizational structure, duties and authorities; a body/committee safeguards impartiality. | I85: Yes | J85: Not started
A86: Governance, Policy & Leadership | B86: ISO/IEC 17021-1 | C86: 8.4 | D86: Confidentiality | E86: ● | H86: The CB keeps information about clients confidential, has a legally enforceable commitment, and informs the client before disclosing to third parties unless required by law. | I86: Yes | J86: Not started
A87: Governance, Policy & Leadership | B87: ISO/IEC 17021-1 | C87: 9.9 | D87: Client records | E87: ● | F87: ● | G87: ● | H87: The CB maintains records of audit and certification for all clients, kept confidential and retained per policy. | I87: Yes | J87: Not started
A88: Governance, Policy & Leadership | B88: GDPR | C88: Art.38 | D88: Position of the DPO | H88: Involve the DPO properly and in a timely manner in all data protection matters; provide resources and independence; DPO reports to highest management level. | I88: Yes | J88: Not started
A89: Governance, Policy & Leadership | B89: ISO/IEC 27701 | C89: 5.2 | D89: Context of the organization (privacy extension) | H89: Extend ISO 27001 4.1-4.4 to consider the organization's role (PII controller and/or processor), applicable privacy laws/regulations (e.g. GDPR, PDPPL), and interested parties relevant to PII processing. | I89: Yes | J89: Not started
A90: Governance, Policy & Leadership | B90: ISO/IEC 27701 | C90: 5.3 | D90: Leadership (privacy extension) | H90: Extend ISO 27001 5.1-5.3 so the information security policy is extended (or a separate privacy policy established) with privacy roles and responsibilities assigned. | I90: Yes | J90: Not started
A91: Governance, Policy & Leadership | B91: Privacy by Design (Cavoukian) | C91: 1.2 | D91: Make privacy a stated organizational commitment | H91: Adopt a documented commitment (policy/charter) that privacy protection is a default objective of every product and process, with leadership accountability. | I91: Yes | J91: Not started
A92: Governance, Policy & Leadership | B92: Privacy by Design (Cavoukian) | C92: 6.2 | D92: Make privacy practices visible to users and stakeholders | H92: Ensure privacy notices, settings and data flows are clear, accessible and accurately reflect what the design actually does - avoid gaps between stated policy and actual behaviour. | I92: Yes | J92: Not started
A93: Governance, Policy & Leadership | B93: DORA | C93: Art.45 | D93: Cyber threat information and intelligence sharing | E93: ● | H93: May voluntarily participate in cyber threat intelligence sharing arrangements with other financial entities, while protecting confidential information and complying with competition rules; participation supports (but does not replace) th... | I93: Yes | J93: Not started
A94: Secure AI Development, Testing & Robustness (29 items across 7 frameworks)
A95: Secure AI Development, Testing & Robustness | B95: ISO/IEC 42001 | C95: A.6.2.4 | D95: AI system verification and validation | E95: ● | F95: ● | G95: ● | H95: Define and document verification/validation measures and criteria (performance, bias, robustness, security testing). | I95: Yes | J95: Not started
A96: Secure AI Development, Testing & Robustness | B96: ISO/IEC 42001 | C96: A.4.6 | D96: Human resources | H96: Document human resources and their competences for development, deployment, operation, change management, maintenance, transfer and decommissioning, and verification and integration of the AI system. | I96: Yes | J96: Not started
A97: Secure AI Development, Testing & Robustness | B97: ISO/IEC 42001 | C97: A.6.1.2 | D97: Objectives for responsible development of AI system | H97: Identify and document objectives guiding responsible AI development (fairness, transparency, robustness, safety, etc.) and integrate them into the life cycle. | I97: Yes | J97: Not started
A98: Secure AI Development, Testing & Robustness | B98: EU AI Act | C98: Art.55 | D98: Obligations for providers of GPAI models with systemic risk | E98: ● | F98: ● | G98: ● | H98: Perform model evaluation incl. adversarial testing, assess and mitigate systemic risks, track/document/report serious incidents, ensure adequate cybersecurity protection for the model and its physical infrastructure. | I98: Yes | J98: Not started
A99: Secure AI Development, Testing & Robustness | B99: NIST AI RMF | C99: Measure 1 | D99: Appropriate methods and metrics are identified and applied to AI risks, and effectiveness of metrics evaluated. | H99: Select and document metrics for measuring AI risks (performance, fairness, robustness, etc.). | I99: Yes | J99: Not started
A100: Secure AI Development, Testing & Robustness | B100: NIST AI RMF | C100: Measure 2 | D100: AI systems are evaluated for trustworthy characteristics: valid/reliable, safe, secure/resilient, accountable/transparent, explainable/interpretable, privacy-enhanced, fair with harmful bias managed. | E100: ● | F100: ● | G100: ● | H100: Test and document evaluation of each trustworthy characteristic, incl. security and resilience testing against adversarial/abuse scenarios. | I100: Yes | J100: Not started
A101: Secure AI Development, Testing & Robustness | B101: NIST AI RMF | C101: Measure 4 | D101: Feedback about efficacy of measurement is gathered and assessed. | H101: Gather feedback (incl. from red-teaming, external audits, user reports) and use it to improve measurement approaches. | I101: Yes | J101: Not started
A102: Secure AI Development, Testing & Robustness | B102: ISO/IEC 27001 | C102: 5.22 | D102: Monitoring, review and change management of supplier services | E102: ● | F102: ● | G102: ● | H102: Regularly monitor, review, evaluate and manage change in supplier practices and service delivery. | I102: Yes | J102: Not started
A103: Secure AI Development, Testing & Robustness | B103: ISO/IEC 27001 | C103: 8.4 | D103: Access to source code | E103: ● | F103: ● | H103: Appropriately manage read/write access to source code, dev tools and libraries. | I103: Yes | J103: Not started
A104: Secure AI Development, Testing & Robustness | B104: ISO/IEC 27001 | C104: 8.8 | D104: Management of technical vulnerabilities | E104: ● | F104: ● | G104: ● | H104: Obtain vulnerability info, assess exposure and take appropriate measures. | I104: Yes | J104: Not started
A105: Secure AI Development, Testing & Robustness | B105: ISO/IEC 27001 | C105: 8.18 | D105: Use of privileged utility programs | E105: ● | F105: ● | G105: ● | H105: Restrict and tightly control utility programs able to override system controls. | I105: Yes | J105: Not started
A106: Secure AI Development, Testing & Robustness | B106: ISO/IEC 27001 | C106: 8.19 | D106: Installation of software on operational systems | F106: ● | H106: Implement procedures to securely manage software installation on operational systems. | I106: Yes | J106: Not started
A107: Secure AI Development, Testing & Robustness | B107: ISO/IEC 27001 | C107: 8.25 | D107: Secure development life cycle | E107: ● | F107: ● | G107: ● | H107: Establish and apply rules for secure development of software and systems. | I107: Yes | J107: Not started
A108: Secure AI Development, Testing & Robustness | B108: ISO/IEC 27001 | C108: 8.26 | D108: Application security requirements | E108: ● | F108: ● | G108: ● | H108: Identify, specify and approve security requirements for applications. | I108: Yes | J108: Not started
A109: Secure AI Development, Testing & Robustness | B109: ISO/IEC 27001 | C109: 8.27 | D109: Secure system architecture and engineering principles | E109: ● | F109: ● | G109: ● | H109: Establish, document, maintain and apply secure engineering principles. | I109: Yes | J109: Not started
A110: Secure AI Development, Testing & Robustness | B110: ISO/IEC 27001 | C110: 8.28 | D110: Secure coding | F110: ● | H110: Apply secure coding principles to software development. | I110: Yes | J110: Not started
A111: Secure AI Development, Testing & Robustness | B111: ISO/IEC 27001 | C111: 8.29 | D111: Security testing in development and acceptance | E111: ● | F111: ● | G111: ● | H111: Define and implement security testing in the development life cycle. | I111: Yes | J111: Not started
A112: Secure AI Development, Testing & Robustness | B112: ISO/IEC 27001 | C112: 8.31 | D112: Separation of development, test and production environments | F112: ● | H112: Separate and secure development, testing and production environments. | I112: Yes | J112: Not started
A113: Secure AI Development, Testing & Robustness | B113: ISO/IEC 27001 | C113: 8.32 | D113: Change management | F113: ● | H113: Subject changes to information processing facilities and systems to change management procedures. | I113: Yes | J113: Not started
A114: Secure AI Development, Testing & Robustness | B114: ISO/IEC 27001 | C114: 8.33 | D114: Test information | E114: ● | H114: Appropriately select, protect and manage test information. | I114: Yes | J114: Not started
A115: Secure AI Development, Testing & Robustness | B115: DORA | C115: Art.9 | D115: Protection and prevention | E115: ● | F115: ● | G115: ● | H115: Implement controls: information security policies/procedures/access controls, network segmentation, encryption/cryptography policies, third-party access policies, change management, document management, patch management, and ICT project ... | I115: Yes | J115: Not started
A116: Secure AI Development, Testing & Robustness | B116: DORA | C116: Art.25 | D116: Testing of ICT tools and systems | E116: ● | F116: ● | G116: ● | H116: Perform a range of basic tests: vulnerability assessments/scans, network security assessments, source code reviews, performance tests, end-to-end tests, and scenario-based compatibility tests. | I116: Yes | J116: Not started
A117: Secure AI Development, Testing & Robustness | B117: NIST ARIA | C117: MT.2 | D117: Align model testing with the 'secure and resilient' trustworthy characteristic | E117: ● | F117: ● | G117: ● | H117: Where model testing covers security-relevant behaviour (robustness to adversarial inputs, resistance to manipulation), ensure this is explicitly scoped alongside functional/accuracy testing. | I117: Yes | J117: Not started
A118: Secure AI Development, Testing & Robustness | B118: NIST ARIA | C118: RT.1 | D118: Establish or engage a red-teaming capability aligned to ARIA's approach | E118: ● | F118: ● | G118: ● | H118: Build (or contract) a red-teaming capability able to rigorously challenge the AI system to surface weaknesses, consistent with ARIA's structured, scenario-based red-teaming methodology. | I118: Yes | J118: Not started
A119: Secure AI Development, Testing & Robustness | B119: NIST ARIA | C119: RT.2 | D119: Scope red-teaming scenarios against known AI risk taxonomies | E119: ● | F119: ● | G119: ● | H119: Design red-team scenarios informed by the NIST AI RMF GenAI Profile risks and, where relevant, the OWASP LLM Top 10 (Tab 10), so red-teaming coverage is traceable to a recognized risk set. | I119: Yes | J119: Not started
A120: Secure AI Development, Testing & Robustness | B120: NIST ARIA | C120: RT.3 | D120: Capture and remediate red-team findings | F120: ● | H120: Document red-teaming findings, prioritise by severity, and track remediation to closure, consistent with how ARIA expects materialized risks to feed back into system improvement. | I120: Yes | J120: Not started
A121: Secure AI Development, Testing & Robustness | B121: NIST ARIA | C121: M.1 | D121: Understand CoRIx as ARIA's composite measurement instrument | H121: Recognize that ARIA scores evaluated systems on the Contextual Robustness Index (CoRIx), a suite of metrics (ARIA documents ten measurement dimensions, including the seven AI RMF trustworthy characteristics - valid/reliable, safe, secure... | I121: Yes | J121: Not started
